{"interfaceLanguages":{"swift":[{"children":[{"title":"Essentials","type":"groupMarker"},{"path":"\/documentation\/bitcoin\/gettingstarted","title":"Getting Started","type":"article"},{"children":[{"title":"Initializers","type":"groupMarker"},{"path":"\/documentation\/bitcoin\/transaction\/init(version:locktime:inputs:outputs:)","title":"init(version: Version, locktime: Locktime, inputs: [Input], outputs: [Output])","type":"init"},{"title":"Instance Properties","type":"groupMarker"},{"path":"\/documentation\/bitcoin\/transaction\/inputs","title":"var inputs: [Input]","type":"property"},{"path":"\/documentation\/bitcoin\/transaction\/locktime","title":"var locktime: Locktime","type":"property"},{"path":"\/documentation\/bitcoin\/transaction\/outputs","title":"var outputs: [Output]","type":"property"},{"path":"\/documentation\/bitcoin\/transaction\/version","title":"let version: Version","type":"property"},{"title":"Default Implementations","type":"groupMarker"},{"children":[{"title":"Operators","type":"groupMarker"},{"path":"\/documentation\/bitcoin\/transaction\/!=(_:_:)","title":"static func != (Self, Self) -> Bool","type":"op"}],"path":"\/documentation\/bitcoin\/transaction\/equatable-implementations","title":"Equatable Implementations","type":"symbol"}],"path":"\/documentation\/bitcoin\/transaction","title":"Transaction","type":"struct"},{"title":"Structures","type":"groupMarker"},{"children":[{"title":"Initializers","type":"groupMarker"},{"path":"\/documentation\/bitcoin\/input\/init(outpoint:sequence:script:witness:)","title":"init(outpoint: Outpoint, sequence: Sequence, script: Data, witness: Witness?)","type":"init"},{"title":"Instance Properties","type":"groupMarker"},{"path":"\/documentation\/bitcoin\/input\/outpoint","title":"var outpoint: Outpoint","type":"property"},{"path":"\/documentation\/bitcoin\/input\/script","title":"var script: Data","type":"property"},{"path":"\/documentation\/bitcoin\/input\/sequence","title":"var sequence: Sequence","type":"property"},{"path":"\/documentation\/bitcoin\/input\/witness","title":"var witness: Witness?","type":"property"},{"title":"Default Implementations","type":"groupMarker"},{"children":[{"title":"Operators","type":"groupMarker"},{"path":"\/documentation\/bitcoin\/input\/!=(_:_:)","title":"static func != (Self, Self) -> Bool","type":"op"}],"path":"\/documentation\/bitcoin\/input\/equatable-implementations","title":"Equatable Implementations","type":"symbol"}],"path":"\/documentation\/bitcoin\/input","title":"Input","type":"struct"},{"children":[{"title":"Initializers","type":"groupMarker"},{"path":"\/documentation\/bitcoin\/locktime\/init(_:)","title":"init(Int)","type":"init"},{"title":"Instance Properties","type":"groupMarker"},{"path":"\/documentation\/bitcoin\/locktime\/locktimevalue","title":"let locktimeValue: Int","type":"property"},{"title":"Default Implementations","type":"groupMarker"},{"children":[{"title":"Operators","type":"groupMarker"},{"path":"\/documentation\/bitcoin\/locktime\/!=(_:_:)","title":"static func != (Self, Self) -> Bool","type":"op"}],"path":"\/documentation\/bitcoin\/locktime\/equatable-implementations","title":"Equatable Implementations","type":"symbol"}],"path":"\/documentation\/bitcoin\/locktime","title":"Locktime","type":"struct"},{"children":[{"title":"Initializers","type":"groupMarker"},{"path":"\/documentation\/bitcoin\/outpoint\/init(transaction:output:)","title":"init(transaction: String, output: Int)","type":"init"},{"title":"Instance Properties","type":"groupMarker"},{"path":"\/documentation\/bitcoin\/outpoint\/output","title":"var output: Int","type":"property"},{"path":"\/documentation\/bitcoin\/outpoint\/transaction","title":"var transaction: String","type":"property"},{"title":"Default Implementations","type":"groupMarker"},{"children":[{"title":"Operators","type":"groupMarker"},{"path":"\/documentation\/bitcoin\/outpoint\/!=(_:_:)","title":"static func != (Self, Self) -> Bool","type":"op"}],"path":"\/documentation\/bitcoin\/outpoint\/equatable-implementations","title":"Equatable Implementations","type":"symbol"}],"path":"\/documentation\/bitcoin\/outpoint","title":"Outpoint","type":"struct"},{"children":[{"title":"Initializers","type":"groupMarker"},{"path":"\/documentation\/bitcoin\/output\/init(value:script:)","title":"init(value: Amount, script: Data)","type":"init"},{"title":"Instance Properties","type":"groupMarker"},{"path":"\/documentation\/bitcoin\/output\/script","title":"var script: Data","type":"property"},{"path":"\/documentation\/bitcoin\/output\/value","title":"var value: Amount","type":"property"},{"title":"Default Implementations","type":"groupMarker"},{"children":[{"title":"Operators","type":"groupMarker"},{"path":"\/documentation\/bitcoin\/output\/!=(_:_:)","title":"static func != (Self, Self) -> Bool","type":"op"}],"path":"\/documentation\/bitcoin\/output\/equatable-implementations","title":"Equatable Implementations","type":"symbol"}],"path":"\/documentation\/bitcoin\/output","title":"Output","type":"struct"},{"children":[{"title":"Initializers","type":"groupMarker"},{"path":"\/documentation\/bitcoin\/sequence\/init(_:)","title":"init(Int)","type":"init"},{"title":"Instance Properties","type":"groupMarker"},{"path":"\/documentation\/bitcoin\/sequence\/sequencevalue","title":"let sequenceValue: Int","type":"property"},{"title":"Default Implementations","type":"groupMarker"},{"children":[{"title":"Operators","type":"groupMarker"},{"path":"\/documentation\/bitcoin\/sequence\/!=(_:_:)","title":"static func != (Self, Self) -> Bool","type":"op"}],"path":"\/documentation\/bitcoin\/sequence\/equatable-implementations","title":"Equatable Implementations","type":"symbol"}],"path":"\/documentation\/bitcoin\/sequence","title":"Sequence","type":"struct"},{"children":[{"title":"Type Properties","type":"groupMarker"},{"path":"\/documentation\/bitcoin\/version\/v1","title":"static let v1: Version","type":"property"},{"title":"Default Implementations","type":"groupMarker"},{"children":[{"title":"Operators","type":"groupMarker"},{"path":"\/documentation\/bitcoin\/version\/!=(_:_:)","title":"static func != (Self, Self) -> Bool","type":"op"}],"path":"\/documentation\/bitcoin\/version\/equatable-implementations","title":"Equatable Implementations","type":"symbol"}],"path":"\/documentation\/bitcoin\/version","title":"Version","type":"struct"},{"children":[{"title":"Initializers","type":"groupMarker"},{"path":"\/documentation\/bitcoin\/witness\/init(_:)","title":"init([Data])","type":"init"},{"title":"Instance Properties","type":"groupMarker"},{"path":"\/documentation\/bitcoin\/witness\/elements","title":"var elements: [Data]","type":"property"},{"title":"Default Implementations","type":"groupMarker"},{"children":[{"title":"Operators","type":"groupMarker"},{"path":"\/documentation\/bitcoin\/witness\/!=(_:_:)","title":"static func != (Self, Self) -> Bool","type":"op"}],"path":"\/documentation\/bitcoin\/witness\/equatable-implementations","title":"Equatable Implementations","type":"symbol"}],"path":"\/documentation\/bitcoin\/witness","title":"Witness","type":"struct"},{"title":"Type Aliases","type":"groupMarker"},{"path":"\/documentation\/bitcoin\/amount","title":"Amount","type":"typealias"}],"path":"\/documentation\/bitcoin","title":"Bitcoin","type":"module"}]},"schemaVersion":{"major":0,"minor":1,"patch":1}}