{"bundleID":"BitcoinBase","version":{"minor":1,"patch":0,"major":0},"nonSymbolPaths":{"248":"\/documentation\/BitcoinBase\/TxWitness\/Equatable-Implementations","178":"\/documentation\/BitcoinBase\/ScriptConfig\/SetAlgebra-Implementations","61":"\/documentation\/BitcoinBase\/TxSequence\/Equatable-Implementations","119":"\/documentation\/BitcoinBase\/SigVersion\/RawRepresentable-Implementations","205":"\/documentation\/BitcoinBase\/TapscriptExtension\/Equatable-Implementations","175":"\/documentation\/BitcoinBase\/TxLocktime\/Equatable-Implementations","339":"\/documentation\/BitcoinBase\/ScriptOp\/Equatable-Implementations","179":"\/tutorials\/BitcoinBase","43":"\/documentation\/BitcoinBase\/BitcoinTx\/Equatable-Implementations","261":"\/documentation\/BitcoinBase\/BitcoinScript\/ExpressibleByArrayLiteral-Implementations","330":"\/documentation\/BitcoinBase\/TxOutpoint\/Equatable-Implementations","29":"\/documentation\/BitcoinBase\/ScriptNum\/Equatable-Implementations","109":"\/documentation\/BitcoinBase\/ScriptConfig\/OptionSet-Implementations","209":"\/documentation\/BitcoinBase\/UnspentOut\/Equatable-Implementations","313":"\/documentation\/BitcoinBase\/TxVersion\/Equatable-Implementations","127":"\/documentation\/BitcoinBase\/ScriptConfig\/Equatable-Implementations","108":"\/tutorials","365":"\/documentation\/BitcoinBase\/SighashType\/Equatable-Implementations","264":"\/documentation\/BitcoinBase#Overview","129":"\/documentation\/BitcoinBase\/TxVersion\/Comparable-Implementations","338":"\/documentation\/BitcoinBase\/BitcoinScript\/Equatable-Implementations","263":"\/documentation\/BitcoinBase\/TxOut\/Equatable-Implementations","340":"\/documentation\/BitcoinBase\/SigVersion\/Equatable-Implementations","35":"\/documentation\/BitcoinBase\/TxIn\/Equatable-Implementations","227":"\/documentation\/BitcoinBase\/ScriptTree\/Equatable-Implementations","4":"\/documentation\/BitcoinBase#Essentials"},"pathHierarchy":{"modules":[232],"articlesContainer":232,"nodes":[{"symbolID":{"interfaceLanguage":"swift","precise":"s:11BitcoinBase13ScriptContextV14programCounterSivp"},"name":"programCounter"},{"disfavored":3,"name":"!=(_:_:)","symbolID":{"precise":"s:SQsE2neoiySbx_xtFZ::SYNTHESIZED::s:11BitcoinBase9ScriptNumV","interfaceLanguage":"swift"}},{"name":"xor","symbolID":{"precise":"s:11BitcoinBase8ScriptOpO3xoryA2CmF","interfaceLanguage":"swift"}},{"name":"check()","symbolID":{"precise":"s:11BitcoinBase0A2TxV5checkyyKF","interfaceLanguage":"swift"}},{"name":"Essentials"},{"name":"init(_:)","symbolID":{"precise":"s:11BitcoinBase0A2TxVyACSg10Foundation4DataVcfc","interfaceLanguage":"swift"}},{"name":"noOp","symbolID":{"precise":"s:11BitcoinBase8ScriptOpO02noD0yA2CmF","interfaceLanguage":"swift"}},{"name":"BitcoinTx","symbolID":{"precise":"s:11BitcoinBase0A2TxV","interfaceLanguage":"swift"},"children":[{"nodeID":323,"kind":"method","hash":"1kvah"},{"hash":"6w3vh","kind":"method","nodeID":69},{"hash":"94tm9","kind":"property","nodeID":70},{"hash":"7zjo2","nodeID":307,"kind":"property"},{"hash":"6uee0","kind":"property","nodeID":19},{"nodeID":43,"kind":"taskGroup"},{"hash":"4l8ly","nodeID":308,"kind":"type.property"},{"hash":"4oac9","nodeID":75,"kind":"property"},{"hash":"i1gn","kind":"type.property","nodeID":30},{"kind":"type.method","hash":"8xa0l","nodeID":164},{"kind":"property","nodeID":16,"hash":"8cc53"},{"kind":"method","hash":"47jht","nodeID":95},{"hash":"7pl9i","nodeID":116,"kind":"type.property"},{"kind":"method","hash":"6xgto","nodeID":31},{"nodeID":214,"kind":"property","hash":"1zxx6"},{"nodeID":353,"kind":"property","hash":"xksv"},{"nodeID":56,"hash":"42xvh","kind":"init"},{"nodeID":309,"kind":"property","hash":"4g30t"},{"hash":"6tg7r","nodeID":186,"kind":"method"},{"nodeID":273,"kind":"property","hash":"30alf"},{"hash":"10mlv","nodeID":325,"kind":"func.op"},{"kind":"type.method","hash":"7znys","nodeID":168},{"hash":"tp5v","kind":"property","nodeID":212},{"hash":"9rj9k","nodeID":226,"kind":"method"},{"hash":"5dbo0","kind":"init","nodeID":5},{"nodeID":26,"kind":"type.method","hash":"5hr44"},{"kind":"property","hash":"ybjz","nodeID":326},{"kind":"method","nodeID":3,"hash":"5nndn"}]},{"symbolID":{"interfaceLanguage":"swift","precise":"s:11BitcoinBase8ScriptOpO14numEqualVerifyyA2CmF"},"name":"numEqualVerify"},{"symbolID":{"interfaceLanguage":"swift","precise":"s:11BitcoinBase8ScriptOpO7successyACs5UInt8VcACmF"},"name":"success(_:)"},{"name":"size","symbolID":{"interfaceLanguage":"swift","precise":"s:11BitcoinBase0A6ScriptV4sizeSivp"}},{"name":"init(tx:txIn:sigVersion:prevout:scriptCode:tapscriptExtension:sighashType:)","symbolID":{"precise":"s:11BitcoinBase7SigHashC2tx0E2In10sigVersion7prevout10scriptCode18tapscriptExtension11sighashTypeAcA0A2TxV_SiAA0cH0OAA0P3OutV10Foundation4DataVSgAA09TapscriptM0VSgAA07SighashO0Vtcfc","interfaceLanguage":"swift"}},{"name":"mul","symbolID":{"interfaceLanguage":"swift","precise":"s:11BitcoinBase8ScriptOpO3mulyA2CmF"}},{"symbolID":{"precise":"s:11BitcoinBase8ScriptOpO3rotyA2CmF","interfaceLanguage":"swift"},"name":"rot"},{"name":"isAnyCanPay","symbolID":{"precise":"s:11BitcoinBase11SighashTypeV11isAnyCanPaySbvp","interfaceLanguage":"swift"}},{"name":"witness","symbolID":{"interfaceLanguage":"swift","precise":"s:11BitcoinBase4TxInV7witnessAA0C7WitnessVSgvp"}},{"name":"isCoinbase","symbolID":{"interfaceLanguage":"swift","precise":"s:11BitcoinBase0A2TxV10isCoinbaseSbvp"}},{"name":"twoDrop","symbolID":{"precise":"s:11BitcoinBase8ScriptOpO7twoDropyA2CmF","interfaceLanguage":"swift"}},{"symbolID":{"interfaceLanguage":"swift","precise":"s:11BitcoinBase11SighashTypeV8isSingleSbvp"},"name":"isSingle"},{"name":"ins","symbolID":{"interfaceLanguage":"swift","precise":"s:11BitcoinBase0A2TxV3insSayAA0C2InVGvp"}},{"name":"pushData1(_:)","symbolID":{"precise":"s:11BitcoinBase8ScriptOpO9pushData1yAC10Foundation4DataVcACmF","interfaceLanguage":"swift"}},{"name":"verNotIf","symbolID":{"interfaceLanguage":"swift","precise":"s:11BitcoinBase8ScriptOpO8verNotIfyA2CmF"}},{"symbolID":{"precise":"s:11BitcoinBase12ScriptConfigV8pushOnlyACvpZ","interfaceLanguage":"swift"},"name":"pushOnly"},{"symbolID":{"interfaceLanguage":"swift","precise":"s:11BitcoinBase9ScriptNumV3oneACvpZ"},"name":"one"},{"name":"union(_:)","disfavored":3,"symbolID":{"interfaceLanguage":"swift","precise":"s:s9OptionSetPsE5unionyxxF::SYNTHESIZED::s:11BitcoinBase12ScriptConfigV"}},{"symbolID":{"precise":"s:11BitcoinBase8ScriptOpO7boolAndyA2CmF","interfaceLanguage":"swift"},"name":"boolAnd"},{"name":"makeCoinbaseTx(blockHeight:pubkey:witnessMerkleRoot:blockSubsidy:)","symbolID":{"precise":"s:11BitcoinBase0A2TxV012makeCoinbaseC011blockHeight6pubkey17witnessMerkleRoot0F7SubsidyACSi_0A6Crypto6PubKeyV10Foundation4DataVSitFZ","interfaceLanguage":"swift"}},{"name":"noOp8","symbolID":{"precise":"s:11BitcoinBase8ScriptOpO5noOp8yA2CmF","interfaceLanguage":"swift"}},{"symbolID":{"interfaceLanguage":"swift","precise":"s:11BitcoinBase10TxOutpointV2tx0E3OutAC10Foundation4DataV_Sitcfc"},"name":"init(tx:txOut:)"},{"name":"Equatable-Implementations"},{"symbolID":{"interfaceLanguage":"swift","precise":"s:11BitcoinBase0A2TxV8idLengthSivpZ"},"name":"idLength"},{"name":"verifyScript(prevouts:config:)","symbolID":{"interfaceLanguage":"swift","precise":"s:11BitcoinBase0A2TxV12verifyScript8prevouts6configSbSayAA0C3OutVG_AA0E6ConfigVtF"}},{"name":"hasAnyCanPay","symbolID":{"interfaceLanguage":"swift","precise":"s:11BitcoinBase11SighashTypeV12hasAnyCanPaySbvp"}},{"symbolID":{"interfaceLanguage":"swift","precise":"s:11BitcoinBase8ScriptOpO4pickyA2CmF"},"name":"pick"},{"symbolID":{"interfaceLanguage":"swift","precise":"s:SQsE2neoiySbx_xtFZ::SYNTHESIZED::s:11BitcoinBase9TxVersionV"},"disfavored":3,"name":"!=(_:_:)"},{"name":"Equatable-Implementations"},{"name":"checkSigVerify","symbolID":{"precise":"s:11BitcoinBase8ScriptOpO14checkSigVerifyyA2CmF","interfaceLanguage":"swift"}},{"name":"ifDup","symbolID":{"precise":"s:11BitcoinBase8ScriptOpO5ifDupyA2CmF","interfaceLanguage":"swift"}},{"symbolID":{"interfaceLanguage":"swift","precise":"s:11BitcoinBase8ScriptOpO4leftyA2CmF"},"name":"left"},{"name":"discourageUpgradableWitnessProgram","symbolID":{"precise":"s:11BitcoinBase12ScriptConfigV34discourageUpgradableWitnessProgramACvpZ","interfaceLanguage":"swift"}},{"symbolID":{"precise":"s:11BitcoinBase8ScriptOpO3notyA2CmF","interfaceLanguage":"swift"},"name":"not"},{"name":"sha1","symbolID":{"interfaceLanguage":"swift","precise":"s:11BitcoinBase8ScriptOpO4sha1yA2CmF"}},{"symbolID":{"interfaceLanguage":"swift","precise":"s:s9OptionSetPss17FixedWidthInteger8RawValueRpzrlExycfc::SYNTHESIZED::s:11BitcoinBase12ScriptConfigV"},"disfavored":3,"name":"init()"},{"name":"Equatable-Implementations"},{"symbolID":{"interfaceLanguage":"swift","precise":"s:SQsE2neoiySbx_xtFZ::SYNTHESIZED::s:11BitcoinBase8ScriptOpO"},"name":"!=(_:_:)","disfavored":3},{"name":"leafs","symbolID":{"precise":"s:11BitcoinBase10ScriptTreeO5leafsSayACGvp","interfaceLanguage":"swift"}},{"symbolID":{"precise":"s:11BitcoinBase10ScriptTreeO12getOutputKey06secretG010Foundation4DataV0A6Crypto06SecretG0V_tF","interfaceLanguage":"swift"},"name":"getOutputKey(secretKey:)"},{"symbolID":{"interfaceLanguage":"swift","precise":"s:11BitcoinBase8ScriptOpO7unknownyACs5UInt8VcACmF"},"name":"unknown(_:)"},{"name":"sigVersion","symbolID":{"precise":"s:11BitcoinBase7SigHashC10sigVersionAA0cF0Ovp","interfaceLanguage":"swift"}},{"disfavored":3,"symbolID":{"precise":"s:SLsE3zzzoiySNyxGx_xtFZ::SYNTHESIZED::s:11BitcoinBase9TxVersionV","interfaceLanguage":"swift"},"name":"...(_:_:)"},{"symbolID":{"precise":"s:11BitcoinBase12ScriptConfigV10cleanStackACvpZ","interfaceLanguage":"swift"},"name":"cleanStack"},{"disfavored":3,"symbolID":{"precise":"s:SYsSHRzSH8RawValueSYRpzrlE4hash4intoys6HasherVz_tF::SYNTHESIZED::s:11BitcoinBase10SigVersionO","interfaceLanguage":"swift"},"name":"hash(into:)"},{"name":"secondFinal","symbolID":{"precise":"s:11BitcoinBase10TxSequenceV11secondFinalACvpZ","interfaceLanguage":"swift"}},{"symbolID":{"precise":"s:11BitcoinBase8ScriptOpO8constantyACs5UInt8VcACmF","interfaceLanguage":"swift"},"name":"constant(_:)"},{"symbolID":{"interfaceLanguage":"swift","precise":"s:11BitcoinBase0A6ScriptVyAC10Foundation4DataVcfc"},"name":"init(_:)"},{"symbolID":{"precise":"s:11BitcoinBase8ScriptOpO19checkMultiSigVerifyyA2CmF","interfaceLanguage":"swift"},"name":"checkMultiSigVerify"},{"name":"init(version:locktime:ins:outs:)","symbolID":{"precise":"s:11BitcoinBase0A2TxV7version8locktime3ins4outsAcA0C7VersionV_AA0C8LocktimeVSayAA0C2InVGSayAA0C3OutVGtcfc","interfaceLanguage":"swift"}},{"symbolID":{"precise":"s:11BitcoinBase8ScriptOpO6rShiftyA2CmF","interfaceLanguage":"swift"},"name":"rShift"},{"children":[{"hash":"32vcs","kind":"property","nodeID":225},{"kind":"property","hash":"4ka67","nodeID":0},{"kind":"property","nodeID":233,"hash":"6idmo"},{"kind":"property","hash":"13lci","nodeID":172},{"kind":"property","hash":"73pr7","nodeID":64},{"kind":"property","nodeID":266,"hash":"49hzj"},{"hash":"43phe","kind":"property","nodeID":300},{"nodeID":176,"hash":"4p8pt","kind":"property"},{"hash":"v1w6","nodeID":359,"kind":"property"},{"nodeID":247,"hash":"8nb8u","kind":"property"},{"nodeID":113,"hash":"kblz","kind":"method"},{"nodeID":321,"kind":"init","hash":"5faqb"}],"symbolID":{"precise":"s:11BitcoinBase13ScriptContextV","interfaceLanguage":"swift"},"name":"ScriptContext"},{"disfavored":3,"symbolID":{"interfaceLanguage":"swift","precise":"s:s10SetAlgebraPsE8isSubset2ofSbx_tF::SYNTHESIZED::s:11BitcoinBase12ScriptConfigV"},"name":"isSubset(of:)"},{"name":"pubKey","symbolID":{"precise":"s:11BitcoinBase8ScriptOpO6pubKeyyA2CmF","interfaceLanguage":"swift"}},{"name":"Equatable-Implementations"},{"name":"intersection(_:)","symbolID":{"interfaceLanguage":"swift","precise":"s:s9OptionSetPsE12intersectionyxxF::SYNTHESIZED::s:11BitcoinBase12ScriptConfigV"},"disfavored":3},{"symbolID":{"precise":"s:11BitcoinBase11SighashTypeV15singleAnyCanPayACvpZ","interfaceLanguage":"swift"},"name":"singleAnyCanPay"},{"name":"config","symbolID":{"precise":"s:11BitcoinBase13ScriptContextV6configAA0C6ConfigVvp","interfaceLanguage":"swift"}},{"children":[{"kind":"property","hash":"5cwpg","nodeID":278},{"kind":"taskGroup","nodeID":263},{"hash":"6qclh","nodeID":281,"kind":"init"},{"nodeID":112,"kind":"func.op","hash":"r4mp"},{"kind":"property","hash":"6xtso","nodeID":284}],"symbolID":{"precise":"s:11BitcoinBase5TxOutV","interfaceLanguage":"swift"},"name":"TxOut"},{"name":"formUnion(_:)","disfavored":3,"symbolID":{"precise":"s:s9OptionSetPss17FixedWidthInteger8RawValueRpzrlE9formUnionyyxF::SYNTHESIZED::s:11BitcoinBase12ScriptConfigV","interfaceLanguage":"swift"}},{"name":"mod","symbolID":{"interfaceLanguage":"swift","precise":"s:11BitcoinBase8ScriptOpO3modyA2CmF"}},{"name":"return","symbolID":{"precise":"s:11BitcoinBase8ScriptOpO6returnyA2CmF","interfaceLanguage":"swift"}},{"name":"checkSequenceLocks(verifyLockTimeSequence:coins:chainTip:previousBlockMedianTimePast:)","symbolID":{"precise":"s:11BitcoinBase0A2TxV18checkSequenceLocks014verifyLockTimeE05coins8chainTip019previousBlockMedianI4PastySb_SDyAA0C8OutpointVAA10UnspentOutVGS2itKF","interfaceLanguage":"swift"}},{"name":"locktime","symbolID":{"interfaceLanguage":"swift","precise":"s:11BitcoinBase0A2TxV8locktimeAA0C8LocktimeVvp"}},{"symbolID":{"interfaceLanguage":"swift","precise":"s:11BitcoinBase8ScriptOpO3addyA2CmF"},"name":"add"},{"symbolID":{"precise":"s:11BitcoinBase0A6ScriptV19segwitPKHScriptCodeyAC10Foundation4DataVFZ","interfaceLanguage":"swift"},"name":"segwitPKHScriptCode(_:)"},{"symbolID":{"interfaceLanguage":"swift","precise":"s:11BitcoinBase7SigHashC2txAA0A2TxVvp"},"name":"tx"},{"symbolID":{"precise":"s:11BitcoinBase8ScriptOpO9pushData2yAC10Foundation4DataVcACmF","interfaceLanguage":"swift"},"name":"pushData2(_:)"},{"name":"witnessID","symbolID":{"interfaceLanguage":"swift","precise":"s:11BitcoinBase0A2TxV9witnessID10Foundation4DataVvp"}},{"name":"outpoint","symbolID":{"interfaceLanguage":"swift","precise":"s:11BitcoinBase4TxInV8outpointAA0C8OutpointVvp"}},{"name":"!=(_:_:)","symbolID":{"precise":"s:SQsE2neoiySbx_xtFZ::SYNTHESIZED::s:11BitcoinBase10SigVersionO","interfaceLanguage":"swift"},"disfavored":3},{"name":"noneAnyCanPay","symbolID":{"precise":"s:11BitcoinBase11SighashTypeV13noneAnyCanPayACvpZ","interfaceLanguage":"swift"}},{"symbolID":{"interfaceLanguage":"swift","precise":"s:11BitcoinBase12ScriptConfigV8rawValueACSi_tcfc"},"name":"init(rawValue:)"},{"name":"witnessV0","symbolID":{"interfaceLanguage":"swift","precise":"s:11BitcoinBase10SigVersionO9witnessV0yA2CmF"}},{"symbolID":{"interfaceLanguage":"swift","precise":"s:SQsE2neoiySbx_xtFZ::SYNTHESIZED::s:11BitcoinBase9TxWitnessV"},"disfavored":3,"name":"!=(_:_:)"},{"symbolID":{"precise":"s:11BitcoinBase11SighashTypeV12allAnyCanPayACvpZ","interfaceLanguage":"swift"},"name":"allAnyCanPay"},{"name":"minClock","symbolID":{"precise":"s:11BitcoinBase10TxLocktimeV8minClockACvpZ","interfaceLanguage":"swift"}},{"name":"set(txIn:sigVersion:prevout:)","symbolID":{"interfaceLanguage":"swift","precise":"s:11BitcoinBase7SigHashC3set4txIn10sigVersion7prevoutySi_AA0cI0OSgAA5TxOutVtF"}},{"symbolID":{"precise":"s:11BitcoinBase12ScriptConfigV9mandatoryACvpZ","interfaceLanguage":"swift"},"name":"mandatory"},{"symbolID":{"interfaceLanguage":"swift","precise":"s:11BitcoinBase10TxLocktimeVyACSicfc"},"name":"init(_:)"},{"name":"or","symbolID":{"precise":"s:11BitcoinBase8ScriptOpO2oryA2CmF","interfaceLanguage":"swift"}},{"symbolID":{"precise":"s:11BitcoinBase12ScriptConfigV19checkLockTimeVerifyACvpZ","interfaceLanguage":"swift"},"name":"checkLockTimeVerify"},{"name":"...(_:)","symbolID":{"precise":"s:SLsE3zzzoPys16PartialRangeFromVyxGxFZ::SYNTHESIZED::s:11BitcoinBase9TxVersionV","interfaceLanguage":"swift"},"disfavored":3},{"symbolID":{"interfaceLanguage":"swift","precise":"s:11BitcoinBase10TxLocktimeV8disabledACvpZ"},"name":"disabled"},{"symbolID":{"precise":"s:11BitcoinBase4TxInV6scriptAA0A6ScriptVvp","interfaceLanguage":"swift"},"name":"script"},{"symbolID":{"precise":"s:11BitcoinBase8ScriptOpO3maxyA2CmF","interfaceLanguage":"swift"},"name":"max"},{"children":[{"kind":"func.op","hash":"19l6l","nodeID":49},{"nodeID":129,"kind":"taskGroup"},{"hash":"17887","kind":"type.property","nodeID":154},{"nodeID":34,"hash":"ouci","kind":"func.op"},{"nodeID":101,"hash":"8rid7","kind":"func.op"},{"hash":"44o1h","nodeID":363,"kind":"property"},{"kind":"taskGroup","nodeID":313},{"kind":"type.property","hash":"13d0t","nodeID":200},{"nodeID":134,"kind":"func.op","hash":"2xzt5"},{"kind":"func.op","hash":"1xs0b","nodeID":259},{"nodeID":150,"hash":"rsx7","kind":"func.op"},{"nodeID":306,"kind":"func.op","hash":"4d65k"},{"hash":"54xin","nodeID":231,"kind":"func.op"},{"nodeID":155,"hash":"1zjro","kind":"func.op"},{"nodeID":89,"hash":"2o07g","kind":"func.op"}],"name":"TxVersion","symbolID":{"precise":"s:11BitcoinBase9TxVersionV","interfaceLanguage":"swift"}},{"children":[{"nodeID":209,"kind":"taskGroup"},{"nodeID":169,"kind":"func.op","hash":"850mo"}],"symbolID":{"interfaceLanguage":"swift","precise":"s:11BitcoinBase10UnspentOutV"},"name":"UnspentOut"},{"name":"sequenceLocks(verifyLockTimeSequence:previousHeights:blockHeight:previousBlockMedianTimePast:)","symbolID":{"precise":"s:11BitcoinBase0A2TxV13sequenceLocks22verifyLockTimeSequence15previousHeights11blockHeight0j11BlockMedianH4PastySb_SaySiGzS2itKF","interfaceLanguage":"swift"}},{"name":"taprootSecretKey(_:)","symbolID":{"precise":"s:13BitcoinCrypto9SecretKeyV0A4BaseE07taprootcD0yAcD10ScriptTreeOSgF","interfaceLanguage":"swift"}},{"symbolID":{"precise":"s:s10SetAlgebraPsE11subtractingyxxF::SYNTHESIZED::s:11BitcoinBase12ScriptConfigV","interfaceLanguage":"swift"},"disfavored":3,"name":"subtracting(_:)"},{"name":"SigVersion","symbolID":{"precise":"s:11BitcoinBase10SigVersionO","interfaceLanguage":"swift"},"children":[{"kind":"taskGroup","nodeID":119},{"hash":"1pyes","kind":"method","nodeID":51},{"nodeID":340,"kind":"taskGroup"},{"kind":"enum.case","hash":"40p9l","nodeID":202},{"hash":"1a1wt","kind":"func.op","nodeID":77},{"nodeID":327,"hash":"7tsaj","kind":"init"},{"hash":"3vdwm","nodeID":332,"kind":"enum.case"},{"nodeID":80,"kind":"enum.case","hash":"47big"},{"hash":"3pmlc","nodeID":124,"kind":"property"}]},{"children":[{"kind":"type.property","hash":"3ykhj","nodeID":83},{"hash":"7o83n","nodeID":185,"kind":"property"},{"nodeID":175,"kind":"taskGroup"},{"hash":"59bjj","nodeID":104,"kind":"func.op"},{"nodeID":115,"kind":"type.property","hash":"6bvcb"},{"kind":"type.property","nodeID":90,"hash":"2d659"},{"kind":"init","hash":"2k0hz","nodeID":86}],"name":"TxLocktime","symbolID":{"interfaceLanguage":"swift","precise":"s:11BitcoinBase10TxLocktimeV"}},{"name":"cat","symbolID":{"interfaceLanguage":"swift","precise":"s:11BitcoinBase8ScriptOpO3catyA2CmF"}},{"disfavored":3,"symbolID":{"precise":"s:SLsE2leoiySbx_xtFZ::SYNTHESIZED::s:11BitcoinBase9TxVersionV","interfaceLanguage":"swift"},"name":"<=(_:_:)"},{"symbolID":{"precise":"s:11BitcoinBase7SigHashC8prevoutsSayAA5TxOutVGvp","interfaceLanguage":"swift"},"name":"prevouts"},{"symbolID":{"precise":"s:11BitcoinBase8ScriptOpO6twoDivyA2CmF","interfaceLanguage":"swift"},"name":"twoDiv"},{"symbolID":{"interfaceLanguage":"swift","precise":"s:SQsE2neoiySbx_xtFZ::SYNTHESIZED::s:11BitcoinBase10TxLocktimeV"},"disfavored":3,"name":"!=(_:_:)"},{"children":[{"nodeID":103,"hash":"6bpbk","kind":"enum.case"},{"nodeID":240,"kind":"enum.case","hash":"5j4s6"},{"hash":"5w91a","nodeID":74,"kind":"enum.case"},{"nodeID":331,"kind":"enum.case","hash":"54rib"},{"nodeID":290,"hash":"sghp","kind":"enum.case"},{"hash":"8ug79","kind":"enum.case","nodeID":292},{"nodeID":280,"kind":"enum.case","hash":"6cf9i"},{"nodeID":294,"kind":"enum.case","hash":"6i7kf"},{"nodeID":8,"hash":"5x3nl","kind":"enum.case"},{"hash":"7q9ep","kind":"enum.case","nodeID":213},{"kind":"enum.case","hash":"7pbcu","nodeID":27},{"hash":"6c4a7","kind":"enum.case","nodeID":303},{"kind":"enum.case","hash":"3p59m","nodeID":302},{"hash":"5xh5","nodeID":117,"kind":"enum.case"},{"nodeID":162,"kind":"enum.case","hash":"48zby"},{"kind":"enum.case","hash":"60q1v","nodeID":286},{"hash":"dl0c","nodeID":12,"kind":"enum.case"},{"kind":"taskGroup","nodeID":339},{"kind":"enum.case","hash":"8702l","nodeID":57},{"hash":"711e5","nodeID":38,"kind":"enum.case"},{"kind":"enum.case","nodeID":275,"hash":"539q1"},{"nodeID":55,"hash":"30k7e","kind":"enum.case"},{"kind":"enum.case","hash":"75etn","nodeID":158},{"hash":"5ltm5","kind":"enum.case","nodeID":234},{"kind":"enum.case","hash":"3pm47","nodeID":120},{"kind":"property","hash":"3w84h","nodeID":198},{"hash":"7bzor","kind":"enum.case","nodeID":141},{"hash":"61t0g","nodeID":250,"kind":"enum.case"},{"nodeID":33,"kind":"enum.case","hash":"7rmd3"},{"hash":"7jxwz","nodeID":343,"kind":"enum.case"},{"kind":"enum.case","nodeID":133,"hash":"zcu7"},{"kind":"enum.case","hash":"3onad","nodeID":41},{"nodeID":2,"kind":"enum.case","hash":"7rq48"},{"nodeID":195,"hash":"5zmof","kind":"enum.case"},{"hash":"1ck1o","kind":"enum.case","nodeID":68},{"kind":"enum.case","nodeID":92,"hash":"77zx5"},{"hash":"763jw","nodeID":170,"kind":"enum.case"},{"hash":"7jgho","nodeID":368,"kind":"enum.case"},{"nodeID":37,"kind":"enum.case","hash":"4uijf"},{"kind":"enum.case","hash":"8yc7x","nodeID":283},{"nodeID":9,"hash":"4q09","kind":"enum.case"},{"nodeID":315,"kind":"enum.case","hash":"6hcc4"},{"kind":"enum.case","hash":"7adll","nodeID":301},{"kind":"enum.case","nodeID":147,"hash":"68pp7"},{"kind":"enum.case","hash":"3wmz3","nodeID":249},{"kind":"enum.case","nodeID":148,"hash":"1xaj8"},{"nodeID":258,"hash":"9k3cf","kind":"enum.case"},{"hash":"40o3b","nodeID":341,"kind":"enum.case"},{"nodeID":128,"hash":"2q4wr","kind":"enum.case"},{"nodeID":239,"kind":"enum.case","hash":"9wbw6"},{"hash":"56en3","kind":"enum.case","nodeID":268},{"hash":"8ig5p","nodeID":257,"kind":"enum.case"},{"kind":"enum.case","hash":"4voky","nodeID":126},{"nodeID":355,"kind":"enum.case","hash":"qscx"},{"kind":"enum.case","hash":"9dn1h","nodeID":201},{"hash":"e1ee","kind":"enum.case","nodeID":223},{"kind":"enum.case","nodeID":21,"hash":"2jtj2"},{"kind":"enum.case","nodeID":151,"hash":"5iw01"},{"kind":"enum.case","hash":"ao9w","nodeID":118},{"kind":"enum.case","nodeID":204,"hash":"48w4h"},{"nodeID":367,"kind":"enum.case","hash":"9y58a"},{"kind":"enum.case","hash":"1f69y","nodeID":287},{"kind":"enum.case","hash":"1od6z","nodeID":110},{"kind":"enum.case","hash":"51xng","nodeID":106},{"nodeID":40,"hash":"3dg9j","kind":"enum.case"},{"hash":"6gzdw","nodeID":206,"kind":"enum.case"},{"nodeID":100,"hash":"3x7ak","kind":"enum.case"},{"hash":"7e1gy","nodeID":304,"kind":"enum.case"},{"hash":"21ofu","nodeID":17,"kind":"enum.case"},{"kind":"enum.case","hash":"zw9n","nodeID":132},{"nodeID":337,"kind":"enum.case","hash":"1qjpd"},{"hash":"488k2","kind":"func.op","nodeID":44},{"nodeID":253,"kind":"enum.case","hash":"qn7q"},{"kind":"enum.case","hash":"7sakk","nodeID":276},{"hash":"6js5c","nodeID":216,"kind":"enum.case"},{"hash":"99umf","nodeID":272,"kind":"enum.case"},{"nodeID":47,"kind":"enum.case","hash":"8g4p9"},{"hash":"4v1dq","nodeID":373,"kind":"enum.case"},{"kind":"enum.case","nodeID":20,"hash":"8g30f"},{"kind":"enum.case","hash":"4vgqr","nodeID":36},{"kind":"enum.case","nodeID":60,"hash":"4yhjk"},{"hash":"5e2l4","nodeID":13,"kind":"enum.case"},{"nodeID":189,"kind":"enum.case","hash":"5ejis"},{"hash":"9tcl6","kind":"enum.case","nodeID":285},{"nodeID":6,"hash":"1l898","kind":"enum.case"},{"nodeID":358,"kind":"enum.case","hash":"6t1al"},{"nodeID":146,"kind":"enum.case","hash":"51qtr"},{"kind":"enum.case","nodeID":334,"hash":"9le7o"},{"hash":"87sof","kind":"enum.case","nodeID":25},{"kind":"enum.case","hash":"5vc4k","nodeID":196},{"kind":"enum.case","hash":"7pwyj","nodeID":192},{"hash":"8dtu2","nodeID":291,"kind":"enum.case"},{"hash":"7bxz7","kind":"enum.case","nodeID":67},{"hash":"9kelb","nodeID":320,"kind":"enum.case"},{"kind":"enum.case","hash":"4ldg2","nodeID":254},{"kind":"enum.case","hash":"a030","nodeID":269},{"hash":"4xvhr","nodeID":71,"kind":"enum.case"},{"kind":"enum.case","hash":"9x6ct","nodeID":123},{"kind":"type.method","nodeID":135,"hash":"4ifyj"},{"hash":"62s7q","kind":"type.method","nodeID":125},{"kind":"enum.case","nodeID":87,"hash":"6kkf0"},{"nodeID":53,"kind":"enum.case","hash":"7sx8t"},{"hash":"7bs6d","nodeID":159,"kind":"enum.case"},{"hash":"86k8a","kind":"enum.case","nodeID":184}],"symbolID":{"interfaceLanguage":"swift","precise":"s:11BitcoinBase8ScriptOpO"},"name":"ScriptOp"},{"name":"numEqual","symbolID":{"interfaceLanguage":"swift","precise":"s:11BitcoinBase8ScriptOpO8numEqualyA2CmF"}},{"symbolID":{"interfaceLanguage":"swift","precise":"s:11BitcoinBase12ScriptConfigV9nullDummyACvpZ"},"name":"nullDummy"},{"name":"tutorials"},{"name":"OptionSet-Implementations"},{"name":"checkSigAdd","symbolID":{"precise":"s:11BitcoinBase8ScriptOpO11checkSigAddyA2CmF","interfaceLanguage":"swift"}},{"disfavored":3,"name":"!=(_:_:)","symbolID":{"precise":"s:SQsE2neoiySbx_xtFZ::SYNTHESIZED::s:11BitcoinBase12ScriptConfigV","interfaceLanguage":"swift"}},{"symbolID":{"interfaceLanguage":"swift","precise":"s:SQsE2neoiySbx_xtFZ::SYNTHESIZED::s:11BitcoinBase5TxOutV"},"name":"!=(_:_:)","disfavored":3},{"name":"run(_:stack:sigVersion:leafVersion:tapLeafHash:)","symbolID":{"precise":"s:11BitcoinBase13ScriptContextV3run_5stack10sigVersion04leafH011tapLeafHashyAA0aC0V_Say10Foundation4DataVGAA03SigH0OSgs5UInt8VSgAMSgtKF","interfaceLanguage":"swift"}},{"children":[{"kind":"taskGroup","nodeID":227},{"kind":"property","hash":"9hbak","nodeID":45},{"hash":"5rb5a","nodeID":46,"kind":"method"},{"hash":"18m8g","kind":"enum.case","nodeID":142},{"kind":"method","hash":"4w3i3","nodeID":318},{"hash":"4r85h","nodeID":319,"kind":"enum.case"},{"hash":"726bw","kind":"func.op","nodeID":182},{"nodeID":237,"kind":"init","hash":"9q17n"}],"symbolID":{"precise":"s:11BitcoinBase10ScriptTreeO","interfaceLanguage":"swift"},"name":"ScriptTree"},{"name":"maxBlock","symbolID":{"precise":"s:11BitcoinBase10TxLocktimeV8maxBlockACvpZ","interfaceLanguage":"swift"}},{"symbolID":{"precise":"s:11BitcoinBase0A2TxV5dummyACvpZ","interfaceLanguage":"swift"},"name":"dummy"},{"name":"twoRot","symbolID":{"interfaceLanguage":"swift","precise":"s:11BitcoinBase8ScriptOpO6twoRotyA2CmF"}},{"symbolID":{"precise":"s:11BitcoinBase8ScriptOpO12zeroNotEqualyA2CmF","interfaceLanguage":"swift"},"name":"zeroNotEqual"},{"name":"RawRepresentable-Implementations"},{"symbolID":{"interfaceLanguage":"swift","precise":"s:11BitcoinBase8ScriptOpO7twoSwapyA2CmF"},"name":"twoSwap"},{"name":"unparsable","symbolID":{"precise":"s:11BitcoinBase0A6ScriptV10unparsable10Foundation4DataVvp","interfaceLanguage":"swift"}},{"disfavored":3,"name":"isDisjoint(with:)","symbolID":{"precise":"s:s10SetAlgebraPsE10isDisjoint4withSbx_tF::SYNTHESIZED::s:11BitcoinBase12ScriptConfigV","interfaceLanguage":"swift"}},{"name":"equalVerify","symbolID":{"interfaceLanguage":"swift","precise":"s:11BitcoinBase8ScriptOpO11equalVerifyyA2CmF"}},{"name":"hashValue","disfavored":3,"symbolID":{"interfaceLanguage":"swift","precise":"s:SYsSHRzSH8RawValueSYRpzrlE04hashB0Sivp::SYNTHESIZED::s:11BitcoinBase10SigVersionO"}},{"name":"encodeMinimally(_:)","symbolID":{"precise":"s:11BitcoinBase8ScriptOpO15encodeMinimallyyAC10Foundation4DataVFZ","interfaceLanguage":"swift"}},{"symbolID":{"interfaceLanguage":"swift","precise":"s:11BitcoinBase8ScriptOpO6noOp10yA2CmF"},"name":"noOp10"},{"name":"Equatable-Implementations"},{"name":"size","symbolID":{"precise":"s:11BitcoinBase8ScriptOpO4sizeyA2CmF","interfaceLanguage":"swift"}},{"name":"Comparable-Implementations"},{"symbolID":{"interfaceLanguage":"swift","precise":"s:11BitcoinBase0A6ScriptVyACSayAA0C2OpOGcfc"},"name":"init(_:)"},{"name":"TxSequence","symbolID":{"interfaceLanguage":"swift","precise":"s:11BitcoinBase10TxSequenceV"},"children":[{"hash":"1lspi","nodeID":188,"kind":"type.property"},{"hash":"6jdd","kind":"property","nodeID":245},{"nodeID":274,"kind":"property","hash":"2k1zq"},{"kind":"taskGroup","nodeID":61},{"kind":"type.property","hash":"3cqnp","nodeID":246},{"kind":"property","hash":"99iiw","nodeID":364},{"hash":"3t41b","nodeID":173,"kind":"type.property"},{"hash":"96dgs","nodeID":262,"kind":"type.property"},{"hash":"5krtg","nodeID":265,"kind":"init"},{"hash":"2h0nu","kind":"type.property","nodeID":345},{"kind":"type.property","nodeID":236,"hash":"9mssc"},{"hash":"8zqal","kind":"init","nodeID":371},{"nodeID":52,"kind":"type.property","hash":"25auf"},{"nodeID":260,"hash":"v2gm","kind":"func.op"},{"hash":"32hk","kind":"type.property","nodeID":310},{"kind":"property","nodeID":311,"hash":"68wni"},{"hash":"2bzc8","nodeID":203,"kind":"init"},{"hash":"6ar59","kind":"property","nodeID":312}]},{"symbolID":{"precise":"s:11BitcoinBase8ScriptOpO6oneSubyA2CmF","interfaceLanguage":"swift"},"name":"oneSub"},{"name":"pushData4(_:)","symbolID":{"interfaceLanguage":"swift","precise":"s:11BitcoinBase8ScriptOpO9pushData4yAC10Foundation4DataVcACmF"}},{"symbolID":{"precise":"s:SLsE3zzloiySnyxGx_xtFZ::SYNTHESIZED::s:11BitcoinBase9TxVersionV","interfaceLanguage":"swift"},"name":"..<(_:_:)","disfavored":3},{"name":"encodeMinimally(_:)","symbolID":{"precise":"s:11BitcoinBase8ScriptOpO15encodeMinimallyyACSiFZ","interfaceLanguage":"swift"}},{"symbolID":{"precise":"s:11BitcoinBase7SigHashC3set4txIn10sigVersion8prevouts10scriptCode18tapscriptExtensionySi_AA0cI0OSgSayAA5TxOutVGSg10Foundation4DataVSgAA09TapscriptN0VSgtF","interfaceLanguage":"swift"},"name":"set(txIn:sigVersion:prevouts:scriptCode:tapscriptExtension:)"},{"symbolID":{"precise":"s:11BitcoinBase12ScriptConfigV9strictDERACvpZ","interfaceLanguage":"swift"},"name":"strictDER"},{"symbolID":{"interfaceLanguage":"swift","precise":"s:11BitcoinBase11ExtendedSigV4data10Foundation4DataVvp"},"name":"data"},{"symbolID":{"precise":"s:11BitcoinBase12ScriptConfigV7taprootACvpZ","interfaceLanguage":"swift"},"name":"taproot"},{"symbolID":{"interfaceLanguage":"swift","precise":"s:11BitcoinBase12ScriptConfigV14strictEncodingACvpZ"},"name":"strictEncoding"},{"name":"zero","symbolID":{"interfaceLanguage":"swift","precise":"s:11BitcoinBase8ScriptOpO4zeroyA2CmF"}},{"symbolID":{"interfaceLanguage":"swift","precise":"s:11BitcoinBase10ScriptTreeO4leafyACSi_10Foundation4DataVtcACmF"},"name":"leaf(_:_:)"},{"name":"none","symbolID":{"interfaceLanguage":"swift","precise":"s:11BitcoinBase11SighashTypeV4noneACvpZ"}},{"symbolID":{"precise":"s:11BitcoinBase18TapscriptExtensionV11tapLeafHash10keyVersion10codesepPosAC10Foundation4DataV_s5UInt8Vs6UInt32Vtcfc","interfaceLanguage":"swift"},"name":"init(tapLeafHash:keyVersion:codesepPos:)"},{"name":"witness","symbolID":{"precise":"s:11BitcoinBase12ScriptConfigV7witnessACvpZ","interfaceLanguage":"swift"}},{"name":"verIf","symbolID":{"interfaceLanguage":"swift","precise":"s:11BitcoinBase8ScriptOpO5verIfyA2CmF"}},{"symbolID":{"precise":"s:11BitcoinBase8ScriptOpO5equalyA2CmF","interfaceLanguage":"swift"},"name":"equal"},{"symbolID":{"interfaceLanguage":"swift","precise":"s:11BitcoinBase8ScriptOpO5noOp5yA2CmF"},"name":"noOp5"},{"name":"checkSequenceVerify","symbolID":{"precise":"s:11BitcoinBase12ScriptConfigV19checkSequenceVerifyACvpZ","interfaceLanguage":"swift"}},{"symbolID":{"interfaceLanguage":"swift","precise":"s:SLsE2geoiySbx_xtFZ::SYNTHESIZED::s:11BitcoinBase9TxVersionV"},"name":">=(_:_:)","disfavored":3},{"symbolID":{"interfaceLanguage":"swift","precise":"s:11BitcoinBase8ScriptOpO4swapyA2CmF"},"name":"swap"},{"name":"SighashType","children":[{"kind":"type.property","nodeID":82,"hash":"2e1g"},{"kind":"type.property","nodeID":187,"hash":"4228t"},{"nodeID":252,"kind":"type.property","hash":"8wxv9"},{"nodeID":365,"kind":"taskGroup"},{"nodeID":163,"hash":"14uh8","kind":"property"},{"kind":"type.property","hash":"7ri6t","nodeID":143},{"kind":"func.op","nodeID":244,"hash":"3mrep"},{"kind":"property","hash":"1523v","nodeID":14},{"kind":"type.property","hash":"a5yb","nodeID":78},{"kind":"type.property","nodeID":63,"hash":"96160"},{"hash":"e95m","kind":"property","nodeID":32},{"nodeID":18,"kind":"property","hash":"10jlt"},{"kind":"property","hash":"9v3u7","nodeID":270},{"kind":"property","hash":"8zsep","nodeID":360}],"symbolID":{"precise":"s:11BitcoinBase11SighashTypeV","interfaceLanguage":"swift"}},{"name":"prevout","symbolID":{"precise":"s:11BitcoinBase7SigHashC7prevoutAA5TxOutVvp","interfaceLanguage":"swift"}},{"name":"v1","symbolID":{"precise":"s:11BitcoinBase9TxVersionV2v1ACvpZ","interfaceLanguage":"swift"}},{"name":"...(_:)","disfavored":3,"symbolID":{"interfaceLanguage":"swift","precise":"s:SLsE3zzzopys19PartialRangeThroughVyxGxFZ::SYNTHESIZED::s:11BitcoinBase9TxVersionV"}},{"symbolID":{"precise":"s:11BitcoinBase10TxOutpointV4txID10Foundation4DataVvp","interfaceLanguage":"swift"},"name":"txID"},{"symbolID":{"precise":"s:11BitcoinBase7SigHashC5value10Foundation4DataVvp","interfaceLanguage":"swift"},"name":"value"},{"name":"min","symbolID":{"interfaceLanguage":"swift","precise":"s:11BitcoinBase8ScriptOpO3minyA2CmF"}},{"name":"sha256","symbolID":{"precise":"s:11BitcoinBase8ScriptOpO6sha256yA2CmF","interfaceLanguage":"swift"}},{"symbolID":{"precise":"s:11BitcoinBase0A6ScriptV3run_2tx0E2In8prevouts5stack10sigVersionSay10Foundation4DataVGAA0C6ConfigV_AA0A2TxVSiSayAA0N3OutVGAmA03SigJ0OtKF","interfaceLanguage":"swift"},"name":"run(_:tx:txIn:prevouts:stack:sigVersion:)"},{"name":"minimalData","symbolID":{"interfaceLanguage":"swift","precise":"s:11BitcoinBase12ScriptConfigV11minimalDataACvpZ"}},{"symbolID":{"precise":"s:11BitcoinBase8ScriptOpO5depthyA2CmF","interfaceLanguage":"swift"},"name":"depth"},{"name":"isAll","symbolID":{"interfaceLanguage":"swift","precise":"s:11BitcoinBase11SighashTypeV5isAllSbvp"}},{"symbolID":{"interfaceLanguage":"swift","precise":"s:11BitcoinBase0A2TxV011makeGenesisC012blockSubsidyACSi_tFZ"},"name":"makeGenesisTx(blockSubsidy:)"},{"name":"init(tx:txIn:sigVersion:prevouts:scriptCode:tapscriptExtension:sighashType:)","symbolID":{"precise":"s:11BitcoinBase7SigHashC2tx0E2In10sigVersion8prevouts10scriptCode18tapscriptExtension11sighashTypeAcA0A2TxV_SiAA0cH0OSayAA0P3OutVG10Foundation4DataVSgAA09TapscriptM0VSgAA07SighashO0VSgtcfc","interfaceLanguage":"swift"}},{"name":"payToScriptHash(_:)","symbolID":{"precise":"s:11BitcoinBase0A6ScriptV05payToC4HashyA2CFZ","interfaceLanguage":"swift"}},{"symbolID":{"precise":"s:11BitcoinBase12ScriptConfigV25discourageUpgradableNoOpsACvpZ","interfaceLanguage":"swift"},"name":"discourageUpgradableNoOps"},{"name":"makeCoinbaseTx(blockHeight:pubkeyHash:witnessMerkleRoot:blockSubsidy:)","symbolID":{"interfaceLanguage":"swift","precise":"s:11BitcoinBase0A2TxV012makeCoinbaseC011blockHeight10pubkeyHash17witnessMerkleRoot0F7SubsidyACSi_10Foundation4DataVAKSitFZ"}},{"disfavored":3,"symbolID":{"precise":"s:SQsE2neoiySbx_xtFZ::SYNTHESIZED::s:11BitcoinBase10UnspentOutV","interfaceLanguage":"swift"},"name":"!=(_:_:)"},{"name":"endIf","symbolID":{"precise":"s:11BitcoinBase8ScriptOpO5endIfyA2CmF","interfaceLanguage":"swift"}},{"symbolID":{"precise":"s:s10SetAlgebraPs7ElementQz012ArrayLiteralC0RtzrlE05arrayE0xAFd_tcfc::SYNTHESIZED::s:11BitcoinBase12ScriptConfigV","interfaceLanguage":"swift"},"name":"init(arrayLiteral:)","disfavored":3},{"name":"stack","symbolID":{"interfaceLanguage":"swift","precise":"s:11BitcoinBase13ScriptContextV5stackSay10Foundation4DataVGvp"}},{"name":"locktimeDisabled","symbolID":{"interfaceLanguage":"swift","precise":"s:11BitcoinBase10TxSequenceV16locktimeDisabledACvpZ"}},{"name":"TxID","symbolID":{"precise":"s:11BitcoinBase4TxIDa","interfaceLanguage":"swift"}},{"name":"Equatable-Implementations"},{"symbolID":{"precise":"s:11BitcoinBase13ScriptContextV2txAA0A2TxVvp","interfaceLanguage":"swift"},"name":"tx"},{"symbolID":{"precise":"s:11BitcoinBase0A6ScriptV11payToPubkeyyAC0A6Crypto6PubKeyVFZ","interfaceLanguage":"swift"},"name":"payToPubkey(_:)"},{"name":"SetAlgebra-Implementations"},{"name":"BitcoinBase"},{"symbolID":{"precise":"s:11BitcoinBase12ScriptConfigV34discourageUpgradableTaprootVersionACvpZ","interfaceLanguage":"swift"},"name":"discourageUpgradableTaprootVersion"},{"symbolID":{"precise":"s:11BitcoinBase12ScriptConfigV8nullFailACvpZ","interfaceLanguage":"swift"},"name":"nullFail"},{"name":"!=(_:_:)","disfavored":3,"symbolID":{"interfaceLanguage":"swift","precise":"s:SQsE2neoiySbx_xtFZ::SYNTHESIZED::s:11BitcoinBase10ScriptTreeO"}},{"name":"update(with:)","disfavored":3,"symbolID":{"interfaceLanguage":"swift","precise":"s:s9OptionSetPs7ElementQzRszrlE6update4withxSgx_tF::SYNTHESIZED::s:11BitcoinBase12ScriptConfigV"}},{"symbolID":{"precise":"s:11BitcoinBase8ScriptOpO7hash160yA2CmF","interfaceLanguage":"swift"},"name":"hash160"},{"name":"locktimeValue","symbolID":{"interfaceLanguage":"swift","precise":"s:11BitcoinBase10TxLocktimeV13locktimeValueSivp"}},{"name":"isFinal(blockHeight:blockTime:)","symbolID":{"interfaceLanguage":"swift","precise":"s:11BitcoinBase0A2TxV7isFinal11blockHeight0F4TimeSbSiSg_AGtF"}},{"symbolID":{"precise":"s:11BitcoinBase11SighashTypeV6singleACvpZ","interfaceLanguage":"swift"},"name":"single"},{"symbolID":{"precise":"s:11BitcoinBase10TxSequenceV18zeroLocktimeBlocksACvpZ","interfaceLanguage":"swift"},"name":"zeroLocktimeBlocks"},{"name":"twoOver","symbolID":{"interfaceLanguage":"swift","precise":"s:11BitcoinBase8ScriptOpO7twoOveryA2CmF"}},{"children":[{"kind":"property","hash":"3gc4w","nodeID":220},{"kind":"taskGroup","nodeID":248},{"kind":"func.op","hash":"5s4x3","nodeID":81},{"kind":"init","hash":"73p4v","nodeID":293}],"name":"TxWitness","symbolID":{"interfaceLanguage":"swift","precise":"s:11BitcoinBase9TxWitnessV"}},{"symbolID":{"interfaceLanguage":"swift","precise":"s:e:s:13BitcoinCrypto6PubKeyV0A4BaseE8tapTweak10merkleRoot10Foundation4DataVAI_tF"},"children":[{"kind":"method","hash":"k6f6","nodeID":197}],"name":"PubKey"},{"name":"noOp7","symbolID":{"precise":"s:11BitcoinBase8ScriptOpO5noOp7yA2CmF","interfaceLanguage":"swift"}},{"children":[{"kind":"type.property","hash":"5cllh","nodeID":208}],"symbolID":{"interfaceLanguage":"swift","precise":"s:e:s:13BitcoinCrypto6AnySigV0A4BaseE30schnorrSignatureExtendedLengthSivpZ"},"name":"AnySig"},{"symbolID":{"interfaceLanguage":"swift","precise":"s:11BitcoinBase7SigHashC18tapscriptExtensionAA09TapscriptF0VSgvp"},"name":"tapscriptExtension"},{"name":"within","symbolID":{"precise":"s:11BitcoinBase8ScriptOpO6withinyA2CmF","interfaceLanguage":"swift"}},{"symbolID":{"interfaceLanguage":"swift","precise":"s:11BitcoinBase8ScriptOpO8lessThanyA2CmF"},"name":"lessThan"},{"symbolID":{"interfaceLanguage":"swift","precise":"s:13BitcoinCrypto6PubKeyV0A4BaseE20computeControlBlocksy10Foundation4DataV10merkleRoot_SayAHG10leafHashesAJ07controlH0tAD10ScriptTreeOSgF"},"name":"computeControlBlocks(_:)"},{"name":"isPush","symbolID":{"interfaceLanguage":"swift","precise":"s:11BitcoinBase8ScriptOpO6isPushSbvp"}},{"name":"init(_:_:)","symbolID":{"interfaceLanguage":"swift","precise":"s:11BitcoinBase11ExtendedSigVyAC0A6Crypto03AnyD0V_AA11SighashTypeVSgtcfc"}},{"symbolID":{"interfaceLanguage":"swift","precise":"s:11BitcoinBase9TxVersionV2v2ACvpZ"},"name":"v2"},{"name":"greaterThanOrEqual","symbolID":{"precise":"s:11BitcoinBase8ScriptOpO18greaterThanOrEqualyA2CmF","interfaceLanguage":"swift"}},{"symbolID":{"interfaceLanguage":"swift","precise":"s:11BitcoinBase10SigVersionO4baseyA2CmF"},"name":"base"},{"symbolID":{"interfaceLanguage":"swift","precise":"s:11BitcoinBase10TxSequenceV14locktimeBlocksACSgSi_tcfc"},"name":"init(locktimeBlocks:)"},{"name":"abs","symbolID":{"precise":"s:11BitcoinBase8ScriptOpO3absyA2CmF","interfaceLanguage":"swift"}},{"name":"Equatable-Implementations"},{"symbolID":{"precise":"s:11BitcoinBase8ScriptOpO3divyA2CmF","interfaceLanguage":"swift"},"name":"div"},{"name":"isEmpty","disfavored":3,"symbolID":{"precise":"s:s10SetAlgebraPsE7isEmptySbvp::SYNTHESIZED::s:11BitcoinBase12ScriptConfigV","interfaceLanguage":"swift"}},{"symbolID":{"precise":"s:13BitcoinCrypto6AnySigV0A4BaseE30schnorrSignatureExtendedLengthSivpZ","interfaceLanguage":"swift"},"name":"schnorrSignatureExtendedLength"},{"name":"Equatable-Implementations"},{"name":"sighashType","symbolID":{"interfaceLanguage":"swift","precise":"s:11BitcoinBase11ExtendedSigV11sighashTypeAA07SighashF0VSgvp"}},{"children":[{"kind":"func.op","nodeID":267,"hash":"4npy6"},{"hash":"imfm","kind":"init","nodeID":144},{"kind":"taskGroup","nodeID":205}],"name":"TapscriptExtension","symbolID":{"interfaceLanguage":"swift","precise":"s:11BitcoinBase18TapscriptExtensionV"}},{"symbolID":{"precise":"s:11BitcoinBase0A2TxV6weightSivp","interfaceLanguage":"swift"},"name":"weight"},{"symbolID":{"interfaceLanguage":"swift","precise":"s:11BitcoinBase8ScriptOpO6negateyA2CmF"},"name":"negate"},{"name":"data","symbolID":{"interfaceLanguage":"swift","precise":"s:11BitcoinBase0A2TxV4data10Foundation4DataVvp"}},{"name":"set(txIn:sigVersion:prevouts:scriptCode:tapscriptExtension:sighashType:)","symbolID":{"precise":"s:11BitcoinBase7SigHashC3set4txIn10sigVersion8prevouts10scriptCode18tapscriptExtension11sighashTypeySi_AA0cI0OSgSayAA5TxOutVGSg10Foundation4DataVSgAA09TapscriptN0VSgAA07SighashP0VSgtF","interfaceLanguage":"swift"}},{"name":"oneNegate","symbolID":{"interfaceLanguage":"swift","precise":"s:11BitcoinBase8ScriptOpO9oneNegateyA2CmF"}},{"name":"payToPubkeyHash(_:)","symbolID":{"interfaceLanguage":"swift","precise":"s:11BitcoinBase0A6ScriptV15payToPubkeyHashyAC0A6Crypto6PubKeyVFZ"}},{"name":"formSymmetricDifference(_:)","symbolID":{"precise":"s:s9OptionSetPss17FixedWidthInteger8RawValueRpzrlE23formSymmetricDifferenceyyxF::SYNTHESIZED::s:11BitcoinBase12ScriptConfigV","interfaceLanguage":"swift"},"disfavored":3},{"symbolID":{"interfaceLanguage":"swift","precise":"s:11BitcoinBase12ScriptConfigV05payToC4HashACvpZ"},"name":"payToScriptHash"},{"symbolID":{"precise":"s:11BitcoinBase9TxWitnessV8elementsSay10Foundation4DataVGvp","interfaceLanguage":"swift"},"name":"elements"},{"name":"TxIn","children":[{"nodeID":76,"kind":"property","hash":"1pu9s"},{"nodeID":15,"hash":"6qgi2","kind":"property"},{"nodeID":91,"kind":"property","hash":"6t24g"},{"nodeID":344,"kind":"init","hash":"2ilku"},{"nodeID":35,"kind":"taskGroup"},{"kind":"func.op","hash":"8f6py","nodeID":357},{"kind":"property","hash":"5hpv","nodeID":374}],"symbolID":{"interfaceLanguage":"swift","precise":"s:11BitcoinBase4TxInV"}},{"symbolID":{"interfaceLanguage":"swift","precise":"s:11BitcoinBase9ScriptNumV_14extendedLength7minimalAC10Foundation4DataV_S2btKcfc"},"name":"init(_:extendedLength:minimal:)"},{"name":"checkLockTimeVerify","symbolID":{"precise":"s:11BitcoinBase8ScriptOpO19checkLockTimeVerifyyA2CmF","interfaceLanguage":"swift"}},{"symbolID":{"interfaceLanguage":"swift","precise":"s:s9OptionSetPss17FixedWidthInteger8RawValueRpzrlE16formIntersectionyyxF::SYNTHESIZED::s:11BitcoinBase12ScriptConfigV"},"name":"formIntersection(_:)","disfavored":3},{"name":"sigVersion","symbolID":{"precise":"s:11BitcoinBase13ScriptContextV10sigVersionAA03SigF0Ovp","interfaceLanguage":"swift"}},{"name":"checkIns(coins:spendHeight:)","symbolID":{"interfaceLanguage":"swift","precise":"s:11BitcoinBase0A2TxV8checkIns5coins11spendHeightySDyAA0C8OutpointVAA10UnspentOutVG_SitKF"}},{"name":"Equatable-Implementations"},{"symbolID":{"precise":"s:11BitcoinBase12ScriptConfigV23witnessCompressedPubkeyACvpZ","interfaceLanguage":"swift"},"name":"witnessCompressedPubkey"},{"name":"discourageUpgradablePubkeyType","symbolID":{"interfaceLanguage":"swift","precise":"s:11BitcoinBase12ScriptConfigV30discourageUpgradablePubkeyTypeACvpZ"}},{"symbolID":{"interfaceLanguage":"swift","precise":"s:13BitcoinCrypto9SecretKeyV0A4BaseE015taprootInternalD0AA03PubD0Vvp"},"name":"taprootInternalKey"},{"name":"<(_:_:)","symbolID":{"precise":"s:11BitcoinBase9TxVersionV1loiySbAC_ACtFZ","interfaceLanguage":"swift"}},{"symbolID":{"interfaceLanguage":"swift","precise":"BitcoinBase"},"name":"BitcoinBase","children":[{"hash":"3e1le","nodeID":295,"kind":"class"},{"hash":"62at8","nodeID":58,"kind":"struct"},{"nodeID":93,"kind":"struct","hash":"7j86s"},{"hash":"7n86a","nodeID":316,"kind":"struct"},{"hash":"zbc8","nodeID":152,"kind":"struct"},{"hash":"7isrl","nodeID":174,"kind":"typealias"},{"hash":"7iha2","nodeID":221,"kind":"struct"},{"kind":"struct","nodeID":242,"hash":"1jlu0"},{"nodeID":4,"kind":"anchor"},{"hash":"5x4j7","kind":"module.extension","nodeID":322},{"kind":"struct","hash":"1gnh6","nodeID":99},{"hash":"9z2y5","kind":"enum","nodeID":105},{"hash":"1ksty","kind":"struct","nodeID":346},{"hash":"323xd","nodeID":98,"kind":"enum"},{"hash":"3limq","nodeID":94,"kind":"struct"},{"nodeID":211,"kind":"struct","hash":"3azxg"},{"kind":"typealias","hash":"9j7lz","nodeID":329},{"hash":"7ho4d","kind":"struct","nodeID":190},{"nodeID":65,"hash":"1egyg","kind":"struct"},{"nodeID":264,"kind":"anchor"},{"nodeID":314,"hash":"3tw85","kind":"struct"},{"nodeID":114,"kind":"enum","hash":"6l9o3"},{"nodeID":7,"kind":"struct","hash":"5c9lw"},{"hash":"58kbh","nodeID":336,"kind":"struct"},{"kind":"struct","hash":"1hrth","nodeID":131}]},{"symbolID":{"precise":"s:11BitcoinBase13ScriptContextV7opIndexSivp","interfaceLanguage":"swift"},"name":"opIndex"},{"name":"notIf","symbolID":{"interfaceLanguage":"swift","precise":"s:11BitcoinBase8ScriptOpO5notIfyA2CmF"}},{"symbolID":{"precise":"s:11BitcoinBase0A6ScriptV12payToTaproot11internalKey6scriptAC0A6Crypto03PubH0V_AA0C4TreeOSgtFZ","interfaceLanguage":"swift"},"name":"payToTaproot(internalKey:script:)"},{"name":"initial","symbolID":{"precise":"s:11BitcoinBase10TxSequenceV7initialACvpZ","interfaceLanguage":"swift"}},{"symbolID":{"precise":"s:11BitcoinBase10ScriptTreeO_11leafVersionACSay10Foundation4DataVG_Sitcfc","interfaceLanguage":"swift"},"name":"init(_:leafVersion:)"},{"name":"isPayToScriptHash","symbolID":{"interfaceLanguage":"swift","precise":"s:11BitcoinBase0A6ScriptV07isPayToC4HashSbvp"}},{"symbolID":{"interfaceLanguage":"swift","precise":"s:11BitcoinBase8ScriptOpO8threeDupyA2CmF"},"name":"threeDup"},{"name":"checkMultiSig","symbolID":{"interfaceLanguage":"swift","precise":"s:11BitcoinBase8ScriptOpO13checkMultiSigyA2CmF"}},{"name":"empty","symbolID":{"interfaceLanguage":"swift","precise":"s:11BitcoinBase0A6ScriptV5emptyACvpZ"}},{"children":[{"kind":"init","nodeID":28,"hash":"54yse"},{"nodeID":350,"kind":"property","hash":"fnf8"},{"kind":"func.op","hash":"6j07w","nodeID":356},{"kind":"taskGroup","nodeID":330},{"hash":"3h5e0","kind":"property","nodeID":156},{"kind":"type.property","nodeID":296,"hash":"3mxv1"}],"symbolID":{"precise":"s:11BitcoinBase10TxOutpointV","interfaceLanguage":"swift"},"name":"TxOutpoint"},{"disfavored":3,"name":"insert(_:)","symbolID":{"precise":"s:s9OptionSetPs7ElementQzRszrlE6insertySb8inserted_x17memberAfterInserttxF::SYNTHESIZED::s:11BitcoinBase12ScriptConfigV","interfaceLanguage":"swift"}},{"disfavored":3,"name":"!=(_:_:)","symbolID":{"precise":"s:SQsE2neoiySbx_xtFZ::SYNTHESIZED::s:11BitcoinBase11SighashTypeV","interfaceLanguage":"swift"}},{"symbolID":{"precise":"s:11BitcoinBase10TxSequenceV18isLocktimeDisabledSbvp","interfaceLanguage":"swift"},"name":"isLocktimeDisabled"},{"name":"zeroLocktimeSeconds","symbolID":{"precise":"s:11BitcoinBase10TxSequenceV19zeroLocktimeSecondsACvpZ","interfaceLanguage":"swift"}},{"symbolID":{"interfaceLanguage":"swift","precise":"s:11BitcoinBase13ScriptContextV10nonPushOpsSivp"},"name":"nonPushOps"},{"name":"Equatable-Implementations"},{"symbolID":{"interfaceLanguage":"swift","precise":"s:11BitcoinBase8ScriptOpO3andyA2CmF"},"name":"and"},{"symbolID":{"precise":"s:11BitcoinBase8ScriptOpO6subStryA2CmF","interfaceLanguage":"swift"},"name":"subStr"},{"name":"payToWitnessPubkeyHash(_:)","symbolID":{"interfaceLanguage":"swift","precise":"s:11BitcoinBase0A6ScriptV22payToWitnessPubkeyHashyAC0A6Crypto6PubKeyVFZ"}},{"name":"all","symbolID":{"interfaceLanguage":"swift","precise":"s:11BitcoinBase11SighashTypeV3allACvpZ"}},{"symbolID":{"precise":"s:11BitcoinBase8ScriptOpO9pushBytesyAC10Foundation4DataVcACmF","interfaceLanguage":"swift"},"name":"pushBytes(_:)"},{"symbolID":{"interfaceLanguage":"swift","precise":"s:11BitcoinBase8ScriptOpO11greaterThanyA2CmF"},"name":"greaterThan"},{"name":"scriptCode","symbolID":{"precise":"s:11BitcoinBase7SigHashC10scriptCode10Foundation4DataVSgvp","interfaceLanguage":"swift"}},{"symbolID":{"interfaceLanguage":"swift","precise":"s:11BitcoinBase7SigHashC11sighashTypeAA07SighashF0VSgvp"},"name":"sighashType"},{"symbolID":{"precise":"s:11BitcoinBase8ScriptOpO3nipyA2CmF","interfaceLanguage":"swift"},"name":"nip"},{"name":"twoMul","symbolID":{"precise":"s:11BitcoinBase8ScriptOpO6twoMulyA2CmF","interfaceLanguage":"swift"}},{"symbolID":{"precise":"s:SLsE1goiySbx_xtFZ::SYNTHESIZED::s:11BitcoinBase9TxVersionV","interfaceLanguage":"swift"},"name":">(_:_:)","disfavored":3},{"name":"!=(_:_:)","disfavored":3,"symbolID":{"precise":"s:SQsE2neoiySbx_xtFZ::SYNTHESIZED::s:11BitcoinBase10TxSequenceV","interfaceLanguage":"swift"}},{"name":"ExpressibleByArrayLiteral-Implementations"},{"name":"maxLocktimeBlocks","symbolID":{"precise":"s:11BitcoinBase10TxSequenceV17maxLocktimeBlocksACvpZ","interfaceLanguage":"swift"}},{"name":"Equatable-Implementations"},{"name":"Overview"},{"name":"init(locktimeSeconds:)","symbolID":{"precise":"s:11BitcoinBase10TxSequenceV15locktimeSecondsACSgSi_tcfc","interfaceLanguage":"swift"}},{"symbolID":{"interfaceLanguage":"swift","precise":"s:11BitcoinBase13ScriptContextV6scriptAA0aC0Vvp"},"name":"script"},{"name":"!=(_:_:)","disfavored":3,"symbolID":{"interfaceLanguage":"swift","precise":"s:SQsE2neoiySbx_xtFZ::SYNTHESIZED::s:11BitcoinBase18TapscriptExtensionV"}},{"name":"codeSeparator","symbolID":{"interfaceLanguage":"swift","precise":"s:11BitcoinBase8ScriptOpO13codeSeparatoryA2CmF"}},{"symbolID":{"precise":"s:11BitcoinBase8ScriptOpO4elseyA2CmF","interfaceLanguage":"swift"},"name":"else"},{"name":"isNone","symbolID":{"precise":"s:11BitcoinBase11SighashTypeV6isNoneSbvp","interfaceLanguage":"swift"}},{"name":"asm(_:)","symbolID":{"interfaceLanguage":"swift","precise":"s:11BitcoinBase0A6ScriptV3asmySSAA10SigVersionOF"}},{"symbolID":{"precise":"s:11BitcoinBase8ScriptOpO6verifyyA2CmF","interfaceLanguage":"swift"},"name":"verify"},{"name":"size","symbolID":{"interfaceLanguage":"swift","precise":"s:11BitcoinBase0A2TxV4sizeSivp"}},{"name":"sequenceValue","symbolID":{"interfaceLanguage":"swift","precise":"s:11BitcoinBase10TxSequenceV13sequenceValueSivp"}},{"symbolID":{"precise":"s:11BitcoinBase8ScriptOpO4tuckyA2CmF","interfaceLanguage":"swift"},"name":"tuck"},{"name":"right","symbolID":{"precise":"s:11BitcoinBase8ScriptOpO5rightyA2CmF","interfaceLanguage":"swift"}},{"disfavored":3,"symbolID":{"interfaceLanguage":"swift","precise":"s:s9OptionSetPs7ElementQzRszrlE6removeyxSgxF::SYNTHESIZED::s:11BitcoinBase12ScriptConfigV"},"name":"remove(_:)"},{"symbolID":{"interfaceLanguage":"swift","precise":"s:11BitcoinBase5TxOutV6scriptAA0A6ScriptVvp"},"name":"script"},{"name":"discourageOpSuccess","symbolID":{"interfaceLanguage":"swift","precise":"s:11BitcoinBase12ScriptConfigV19discourageOpSuccessACvpZ"}},{"name":"noOp6","symbolID":{"interfaceLanguage":"swift","precise":"s:11BitcoinBase8ScriptOpO5noOp6yA2CmF"}},{"symbolID":{"precise":"s:11BitcoinBase5TxOutV5value6scriptACSi_AA0A6ScriptVtcfc","interfaceLanguage":"swift"},"name":"init(value:script:)"},{"symbolID":{"interfaceLanguage":"swift","precise":"s:11BitcoinBase0A6ScriptV3opsSayAA0C2OpOGvp"},"name":"ops"},{"symbolID":{"precise":"s:11BitcoinBase8ScriptOpO6lShiftyA2CmF","interfaceLanguage":"swift"},"name":"lShift"},{"symbolID":{"precise":"s:11BitcoinBase5TxOutV5valueSivp","interfaceLanguage":"swift"},"name":"value"},{"name":"lessThanOrEqual","symbolID":{"interfaceLanguage":"swift","precise":"s:11BitcoinBase8ScriptOpO15lessThanOrEqualyA2CmF"}},{"name":"oneAdd","symbolID":{"precise":"s:11BitcoinBase8ScriptOpO6oneAddyA2CmF","interfaceLanguage":"swift"}},{"symbolID":{"interfaceLanguage":"swift","precise":"s:11BitcoinBase8ScriptOpO3subyA2CmF"},"name":"sub"},{"name":"rawValue","symbolID":{"precise":"s:11BitcoinBase12ScriptConfigV8rawValueSivp","interfaceLanguage":"swift"}},{"name":"contains(_:)","symbolID":{"precise":"s:s9OptionSetPs7ElementQzRszrlE8containsySbxF::SYNTHESIZED::s:11BitcoinBase12ScriptConfigV","interfaceLanguage":"swift"},"disfavored":3},{"name":"checkSequenceVerify","symbolID":{"interfaceLanguage":"swift","precise":"s:11BitcoinBase8ScriptOpO19checkSequenceVerifyyA2CmF"}},{"name":"if","symbolID":{"precise":"s:11BitcoinBase8ScriptOpO2ifyA2CmF","interfaceLanguage":"swift"}},{"name":"noOp4","symbolID":{"interfaceLanguage":"swift","precise":"s:11BitcoinBase8ScriptOpO5noOp4yA2CmF"}},{"symbolID":{"interfaceLanguage":"swift","precise":"s:11BitcoinBase9TxWitnessVyACSay10Foundation4DataVGcfc"},"name":"init(_:)"},{"name":"checkSig","symbolID":{"precise":"s:11BitcoinBase8ScriptOpO8checkSigyA2CmF","interfaceLanguage":"swift"}},{"children":[{"nodeID":256,"hash":"4wvw","kind":"property"},{"kind":"method","nodeID":84,"hash":"2akm8"},{"hash":"4xlgr","nodeID":102,"kind":"property"},{"nodeID":157,"kind":"property","hash":"9kh6o"},{"kind":"method","hash":"388lv","nodeID":136},{"nodeID":73,"kind":"property","hash":"3jeyq"},{"nodeID":255,"hash":"87i7b","kind":"property"},{"hash":"305","nodeID":153,"kind":"property"},{"nodeID":165,"kind":"init","hash":"48pbx"},{"nodeID":215,"kind":"method","hash":"6reze"},{"hash":"8pw8i","nodeID":11,"kind":"init"},{"nodeID":194,"kind":"property","hash":"8wjjo"},{"kind":"property","hash":"2mz2t","nodeID":48}],"symbolID":{"precise":"s:11BitcoinBase7SigHashC","interfaceLanguage":"swift"},"name":"SigHash"},{"symbolID":{"interfaceLanguage":"swift","precise":"s:11BitcoinBase10TxOutpointV8coinbaseACvpZ"},"name":"coinbase"},{"symbolID":{"interfaceLanguage":"swift","precise":"s:11BitcoinBase12ScriptConfigV08constantC4CodeACvpZ"},"name":"constantScriptCode"},{"symbolID":{"interfaceLanguage":"swift","precise":"s:11BitcoinBase9ScriptNumV11negativeOneACvpZ"},"name":"negativeOne"},{"name":"symmetricDifference(_:)","disfavored":3,"symbolID":{"precise":"s:s9OptionSetPsE19symmetricDifferenceyxxF::SYNTHESIZED::s:11BitcoinBase12ScriptConfigV","interfaceLanguage":"swift"}},{"symbolID":{"precise":"s:11BitcoinBase13ScriptContextV8prevoutsSayAA5TxOutVGvp","interfaceLanguage":"swift"},"name":"prevouts"},{"symbolID":{"precise":"s:11BitcoinBase8ScriptOpO3dupyA2CmF","interfaceLanguage":"swift"},"name":"dup"},{"name":"over","symbolID":{"interfaceLanguage":"swift","precise":"s:11BitcoinBase8ScriptOpO4overyA2CmF"}},{"name":"boolOr","symbolID":{"interfaceLanguage":"swift","precise":"s:11BitcoinBase8ScriptOpO6boolOryA2CmF"}},{"symbolID":{"precise":"s:11BitcoinBase8ScriptOpO12fromAltStackyA2CmF","interfaceLanguage":"swift"},"name":"fromAltStack"},{"symbolID":{"interfaceLanguage":"swift","precise":"s:11BitcoinBase0A6ScriptV4data10Foundation4DataVvp"},"name":"data"},{"name":"..<(_:)","disfavored":3,"symbolID":{"precise":"s:SLsE3zzlopys16PartialRangeUpToVyxGxFZ::SYNTHESIZED::s:11BitcoinBase9TxVersionV","interfaceLanguage":"swift"}},{"name":"outs","symbolID":{"precise":"s:11BitcoinBase0A2TxV4outsSayAA0C3OutVGvp","interfaceLanguage":"swift"}},{"name":"coinbaseWitnessID","symbolID":{"precise":"s:11BitcoinBase0A2TxV17coinbaseWitnessID10Foundation4DataVvpZ","interfaceLanguage":"swift"}},{"name":"version","symbolID":{"precise":"s:11BitcoinBase0A2TxV7versionAA0C7VersionVvp","interfaceLanguage":"swift"}},{"symbolID":{"precise":"s:11BitcoinBase10TxSequenceV5finalACvpZ","interfaceLanguage":"swift"},"name":"final"},{"name":"locktimeBlocks","symbolID":{"interfaceLanguage":"swift","precise":"s:11BitcoinBase10TxSequenceV14locktimeBlocksSiSgvp"}},{"symbolID":{"precise":"s:11BitcoinBase10TxSequenceV16isLocktimeBlocksSbvp","interfaceLanguage":"swift"},"name":"isLocktimeBlocks"},{"name":"Equatable-Implementations"},{"name":"BitcoinScript","symbolID":{"interfaceLanguage":"swift","precise":"s:11BitcoinBase0A6ScriptV"},"children":[{"nodeID":354,"kind":"type.method","hash":"2s5up"},{"nodeID":366,"kind":"func.op","hash":"8kmv9"},{"nodeID":271,"hash":"3n4y0","kind":"method"},{"hash":"6ed4s","nodeID":217,"kind":"type.method"},{"nodeID":160,"hash":"6qho9","kind":"method"},{"hash":"2yixz","kind":"type.method","nodeID":361},{"nodeID":10,"kind":"property","hash":"5wbc"},{"kind":"property","hash":"26nns","nodeID":121},{"nodeID":338,"kind":"taskGroup"},{"kind":"type.method","nodeID":177,"hash":"2gcf6"},{"nodeID":241,"hash":"7hw31","kind":"type.property"},{"kind":"type.method","hash":"w6z","nodeID":166},{"nodeID":238,"hash":"1rs65","kind":"property"},{"kind":"init","hash":"3nux5","nodeID":130},{"kind":"init","hash":"1ausc","nodeID":54},{"kind":"property","nodeID":282,"hash":"56lwz"},{"hash":"8npbp","nodeID":362,"kind":"init"},{"hash":"96cqz","nodeID":72,"kind":"type.method"},{"hash":"8rcdc","kind":"property","nodeID":305},{"kind":"taskGroup","nodeID":261},{"hash":"25ybk","kind":"type.method","nodeID":251},{"kind":"type.method","nodeID":324,"hash":"3kw3w"},{"nodeID":235,"kind":"type.method","hash":"5g54i"}]},{"symbolID":{"precise":"s:11BitcoinBase8ScriptOpO4rollyA2CmF","interfaceLanguage":"swift"},"name":"roll"},{"name":"ScriptConfig","children":[{"hash":"8bugv","nodeID":161,"kind":"type.property"},{"kind":"init","nodeID":79,"hash":"2ckna"},{"hash":"96nie","nodeID":62,"kind":"method"},{"hash":"3ec94","nodeID":181,"kind":"type.property"},{"kind":"method","nodeID":335,"hash":"94ex3"},{"hash":"96cni","nodeID":370,"kind":"method"},{"nodeID":178,"kind":"taskGroup"},{"kind":"type.property","hash":"4m3jq","nodeID":180},{"kind":"method","nodeID":289,"hash":"3fc23"},{"kind":"func.op","nodeID":111,"hash":"40mc0"},{"kind":"type.property","hash":"52w10","nodeID":107},{"hash":"4qxhz","nodeID":351,"kind":"type.property"},{"nodeID":279,"kind":"type.property","hash":"7o3gc"},{"hash":"1ddsz","nodeID":88,"kind":"type.property"},{"kind":"method","hash":"6wrz1","nodeID":299},{"nodeID":149,"kind":"type.property","hash":"5g6lk"},{"kind":"method","nodeID":24,"hash":"1r56t"},{"kind":"taskGroup","nodeID":127},{"nodeID":167,"kind":"type.property","hash":"1ltpu"},{"kind":"type.property","nodeID":297,"hash":"2h5g7"},{"hash":"44c2g","nodeID":122,"kind":"method"},{"hash":"40ee0","kind":"type.property","nodeID":229},{"kind":"type.property","nodeID":137,"hash":"8j5o5"},{"hash":"6uxzu","nodeID":59,"kind":"method"},{"nodeID":140,"hash":"51ud0","kind":"type.property"},{"hash":"7z1wx","kind":"init","nodeID":171},{"kind":"type.property","hash":"3uldf","nodeID":372},{"hash":"6alop","kind":"property","nodeID":207},{"kind":"taskGroup","nodeID":109},{"kind":"method","nodeID":97,"hash":"2xsyt"},{"kind":"type.property","hash":"hhmx","nodeID":145},{"kind":"type.property","hash":"30jh","nodeID":139},{"kind":"method","nodeID":328,"hash":"xel6"},{"kind":"type.property","nodeID":50,"hash":"7wgnn"},{"nodeID":183,"kind":"method","hash":"7apnu"},{"hash":"9tim5","kind":"method","nodeID":66},{"kind":"method","nodeID":277,"hash":"4amjy"},{"nodeID":333,"hash":"14hf0","kind":"type.property"},{"hash":"5vth4","nodeID":288,"kind":"property"},{"nodeID":39,"hash":"8n8n2","kind":"type.property"},{"kind":"method","hash":"71hel","nodeID":224},{"kind":"method","nodeID":218,"hash":"8r8we"},{"nodeID":42,"kind":"init","hash":"7sxps"},{"nodeID":85,"kind":"type.property","hash":"9z2nt"},{"kind":"method","nodeID":243,"hash":"4oflt"},{"nodeID":369,"kind":"method","hash":"avqe"},{"nodeID":22,"kind":"type.property","hash":"8vr94"},{"kind":"type.property","nodeID":219,"hash":"7k8pb"},{"nodeID":228,"kind":"type.property","hash":"9ki7k"},{"hash":"3v542","nodeID":349,"kind":"init"}],"symbolID":{"precise":"s:11BitcoinBase12ScriptConfigV","interfaceLanguage":"swift"}},{"symbolID":{"precise":"s:11BitcoinBase9ScriptNumV5valueSivp","interfaceLanguage":"swift"},"name":"value"},{"symbolID":{"precise":"s:11BitcoinBase10ScriptTreeO14calcMerkleRootSayAC_10Foundation4DataVtG_AGtyF","interfaceLanguage":"swift"},"name":"calcMerkleRoot()"},{"name":"branch(_:_:)","symbolID":{"precise":"s:11BitcoinBase10ScriptTreeO6branchyA2C_ACtcACmF","interfaceLanguage":"swift"}},{"name":"twoDup","symbolID":{"precise":"s:11BitcoinBase8ScriptOpO6twoDupyA2CmF","interfaceLanguage":"swift"}},{"name":"init(_:tx:txIn:prevouts:)","symbolID":{"precise":"s:11BitcoinBase13ScriptContextV_2tx0E2In8prevoutsAcA0C6ConfigV_AA0A2TxVSiSayAA0I3OutVGtcfc","interfaceLanguage":"swift"}},{"children":[{"kind":"struct.extension","nodeID":193,"hash":"2xtsf"},{"kind":"struct.extension","hash":"3qpj0","nodeID":352},{"hash":"1x7uw","nodeID":191,"kind":"struct.extension"}],"name":"BitcoinCrypto","symbolID":{"precise":"s:m:s:e:s:13BitcoinCrypto6AnySigV0A4BaseE30schnorrSignatureExtendedLengthSivpZ","interfaceLanguage":"swift"}},{"symbolID":{"interfaceLanguage":"swift","precise":"s:11BitcoinBase0A2TxV8outpointyAA0C8OutpointVSiF"},"name":"outpoint(_:)"},{"name":"payToMultiSignature(_:of:)","symbolID":{"precise":"s:11BitcoinBase0A6ScriptV19payToMultiSignature_2ofACSi_0A6Crypto6PubKeyVdtFZ","interfaceLanguage":"swift"}},{"name":"!=(_:_:)","symbolID":{"interfaceLanguage":"swift","precise":"s:SQsE2neoiySbx_xtFZ::SYNTHESIZED::s:11BitcoinBase0A2TxV"},"disfavored":3},{"symbolID":{"interfaceLanguage":"swift","precise":"s:11BitcoinBase0A2TxV11virtualSizeSivp"},"name":"virtualSize"},{"name":"init(rawValue:)","symbolID":{"interfaceLanguage":"swift","precise":"s:11BitcoinBase10SigVersionO8rawValueACSgSS_tcfc"}},{"disfavored":3,"symbolID":{"interfaceLanguage":"swift","precise":"s:s10SetAlgebraPsE14isStrictSubset2ofSbx_tF::SYNTHESIZED::s:11BitcoinBase12ScriptConfigV"},"name":"isStrictSubset(of:)"},{"symbolID":{"interfaceLanguage":"swift","precise":"s:11BitcoinBase13SatoshiAmounta"},"name":"SatoshiAmount"},{"name":"Equatable-Implementations"},{"name":"invalidOpCode","symbolID":{"precise":"s:11BitcoinBase8ScriptOpO07invalidD4CodeyA2CmF","interfaceLanguage":"swift"}},{"name":"witnessV1","symbolID":{"interfaceLanguage":"swift","precise":"s:11BitcoinBase10SigVersionO9witnessV1yA2CmF"}},{"symbolID":{"precise":"s:11BitcoinBase12ScriptConfigV9minimalIfACvpZ","interfaceLanguage":"swift"},"name":"minimalIf"},{"name":"noOp9","symbolID":{"precise":"s:11BitcoinBase8ScriptOpO5noOp9yA2CmF","interfaceLanguage":"swift"}},{"disfavored":3,"symbolID":{"interfaceLanguage":"swift","precise":"s:s10SetAlgebraPsE10isSuperset2ofSbx_tF::SYNTHESIZED::s:11BitcoinBase12ScriptConfigV"},"name":"isSuperset(of:)"},{"children":[{"nodeID":342,"hash":"3j800","kind":"property"},{"hash":"9d7ui","nodeID":210,"kind":"property"},{"hash":"8oqld","nodeID":199,"kind":"init"},{"hash":"1b7kj","kind":"property","nodeID":138}],"symbolID":{"precise":"s:11BitcoinBase11ExtendedSigV","interfaceLanguage":"swift"},"name":"ExtendedSig"},{"name":"invert","symbolID":{"interfaceLanguage":"swift","precise":"s:11BitcoinBase8ScriptOpO6invertyA2CmF"}},{"name":"Equatable-Implementations"},{"name":"Equatable-Implementations"},{"name":"Equatable-Implementations"},{"symbolID":{"precise":"s:11BitcoinBase8ScriptOpO10toAltStackyA2CmF","interfaceLanguage":"swift"},"name":"toAltStack"},{"symbolID":{"precise":"s:11BitcoinBase11ExtendedSigV3sig0A6Crypto03AnyD0Vvp","interfaceLanguage":"swift"},"name":"sig"},{"symbolID":{"interfaceLanguage":"swift","precise":"s:11BitcoinBase8ScriptOpO11numNotEqualyA2CmF"},"name":"numNotEqual"},{"name":"init(outpoint:sequence:script:witness:)","symbolID":{"precise":"s:11BitcoinBase4TxInV8outpoint8sequence6script7witnessAcA0C8OutpointV_AA0C8SequenceVAA0A6ScriptVAA0C7WitnessVSgtcfc","interfaceLanguage":"swift"}},{"symbolID":{"precise":"s:11BitcoinBase10TxSequenceV18maxLocktimeSecondsACvpZ","interfaceLanguage":"swift"},"name":"maxLocktimeSeconds"},{"symbolID":{"precise":"s:11BitcoinBase9ScriptNumV","interfaceLanguage":"swift"},"children":[{"hash":"5chr9","nodeID":298,"kind":"type.property"},{"kind":"property","hash":"9fjvt","nodeID":317},{"kind":"init","hash":"1rbtc","nodeID":348},{"hash":"8rd5p","nodeID":1,"kind":"func.op"},{"kind":"type.property","nodeID":23,"hash":"4evhr"},{"hash":"3mbor","kind":"init","nodeID":222},{"kind":"taskGroup","nodeID":29},{"nodeID":347,"kind":"type.property","hash":"1ohh6"}],"name":"ScriptNum"},{"symbolID":{"precise":"s:11BitcoinBase9ScriptNumV4zeroACvpZ","interfaceLanguage":"swift"},"name":"zero"},{"name":"init(_:)","symbolID":{"precise":"s:11BitcoinBase9ScriptNumVyACSiKcfc","interfaceLanguage":"swift"}},{"disfavored":3,"name":"init(_:)","symbolID":{"interfaceLanguage":"swift","precise":"s:s10SetAlgebraPsEyxqd__ncSTRd__7ElementQyd__ACRtzlufc::SYNTHESIZED::s:11BitcoinBase12ScriptConfigV"}},{"symbolID":{"precise":"s:11BitcoinBase10TxOutpointV5txOutSivp","interfaceLanguage":"swift"},"name":"txOut"},{"name":"standard","symbolID":{"interfaceLanguage":"swift","precise":"s:11BitcoinBase12ScriptConfigV8standardACvpZ"}},{"children":[{"hash":"5eh4l","kind":"method","nodeID":96},{"nodeID":230,"kind":"property","hash":"7zdfu"}],"name":"SecretKey","symbolID":{"precise":"s:e:s:13BitcoinCrypto9SecretKeyV0A4BaseE015taprootInternalD0AA03PubD0Vvp","interfaceLanguage":"swift"}},{"symbolID":{"precise":"s:11BitcoinBase0A2TxV2id10Foundation4DataVvp","interfaceLanguage":"swift"},"name":"id"},{"name":"dataCarrier(_:)","symbolID":{"interfaceLanguage":"swift","precise":"s:11BitcoinBase0A6ScriptV11dataCarrieryACSSFZ"}},{"symbolID":{"precise":"s:11BitcoinBase8ScriptOpO4dropyA2CmF","interfaceLanguage":"swift"},"name":"drop"},{"symbolID":{"precise":"s:SQsE2neoiySbx_xtFZ::SYNTHESIZED::s:11BitcoinBase10TxOutpointV","interfaceLanguage":"swift"},"name":"!=(_:_:)","disfavored":3},{"name":"!=(_:_:)","disfavored":3,"symbolID":{"precise":"s:SQsE2neoiySbx_xtFZ::SYNTHESIZED::s:11BitcoinBase4TxInV","interfaceLanguage":"swift"}},{"name":"ripemd160","symbolID":{"interfaceLanguage":"swift","precise":"s:11BitcoinBase8ScriptOpO9ripemd160yA2CmF"}},{"symbolID":{"precise":"s:11BitcoinBase13ScriptContextV4txInSivp","interfaceLanguage":"swift"},"name":"txIn"},{"symbolID":{"interfaceLanguage":"swift","precise":"s:11BitcoinBase11SighashTypeV5values5UInt8Vvp"},"name":"value"},{"symbolID":{"interfaceLanguage":"swift","precise":"s:11BitcoinBase0A6ScriptV012payToWitnessC4HashyA2CFZ"},"name":"payToWitnessScriptHash(_:)"},{"symbolID":{"interfaceLanguage":"swift","precise":"s:11BitcoinBase0A6ScriptV12arrayLiteralAcA0C2OpOd_tcfc"},"name":"init(arrayLiteral:)"},{"name":"versionValue","symbolID":{"interfaceLanguage":"swift","precise":"s:11BitcoinBase9TxVersionV12versionValueSivp"}},{"name":"locktimeSeconds","symbolID":{"precise":"s:11BitcoinBase10TxSequenceV15locktimeSecondsSiSgvp","interfaceLanguage":"swift"}},{"name":"Equatable-Implementations"},{"symbolID":{"precise":"s:SQsE2neoiySbx_xtFZ::SYNTHESIZED::s:11BitcoinBase0A6ScriptV","interfaceLanguage":"swift"},"name":"!=(_:_:)","disfavored":3},{"name":"noOp1","symbolID":{"precise":"s:11BitcoinBase8ScriptOpO5noOp1yA2CmF","interfaceLanguage":"swift"}},{"symbolID":{"precise":"s:11BitcoinBase8ScriptOpO10pubKeyHashyA2CmF","interfaceLanguage":"swift"},"name":"pubKeyHash"},{"disfavored":3,"symbolID":{"precise":"s:s10SetAlgebraPsE8subtractyyxF::SYNTHESIZED::s:11BitcoinBase12ScriptConfigV","interfaceLanguage":"swift"},"name":"subtract(_:)"},{"name":"isStrictSuperset(of:)","disfavored":3,"symbolID":{"precise":"s:s10SetAlgebraPsE16isStrictSuperset2ofSbx_tF::SYNTHESIZED::s:11BitcoinBase12ScriptConfigV","interfaceLanguage":"swift"}},{"name":"init(_:)","symbolID":{"interfaceLanguage":"swift","precise":"s:11BitcoinBase10TxSequenceVyACSicfc"}},{"symbolID":{"interfaceLanguage":"swift","precise":"s:11BitcoinBase12ScriptConfigV4lowSACvpZ"},"name":"lowS"},{"name":"hash256","symbolID":{"precise":"s:11BitcoinBase8ScriptOpO7hash256yA2CmF","interfaceLanguage":"swift"}},{"symbolID":{"precise":"s:11BitcoinBase4TxInV8sequenceAA0C8SequenceVvp","interfaceLanguage":"swift"},"name":"sequence"}],"tutorialContainer":179,"tutorialOverviewContainer":108}}