{"bundleID":"Bitcoin","version":{"major":0,"minor":1,"patch":0},"nonSymbolPaths":{"0":"\/documentation\/Bitcoin\/GettingStarted#Add-the-package","12":"\/documentation\/Bitcoin\/GettingStarted#Mine-a-transaction","25":"\/documentation\/Bitcoin\/Building#Executable-image","21":"\/documentation\/Bitcoin\/Running#Simulate-a-muilt-node-network","15":"\/documentation\/Bitcoin\/Running#Run-using-the-swift-command","18":"\/tutorials\/Bitcoin","23":"\/documentation\/Bitcoin\/Running#Interactive-container","19":"\/documentation\/Bitcoin\/Running#Run-with-docker","5":"\/documentation\/Bitcoin\/Running#Build-executable-docker-images","1":"\/documentation\/Bitcoin\/Building#Mac","16":"\/documentation\/Bitcoin\/Building","22":"\/documentation\/Bitcoin\/Running#Build-and-run-executables-directly","9":"\/documentation\/Bitcoin#Overview","14":"\/documentation\/Bitcoin#Essentials","2":"\/documentation\/Bitcoin\/Running","24":"\/documentation\/Bitcoin\/Building#Linux","20":"\/documentation\/Bitcoin\/Running#Bob","6":"\/documentation\/Bitcoin\/GettingStarted#Preparation","4":"\/documentation\/Bitcoin\/GettingStarted","10":"\/documentation\/Bitcoin\/Running#Carol-Bitcoin-Core","13":"\/documentation\/Bitcoin\/Building#Docker-instructions","8":"\/documentation\/Bitcoin\/Running#Setup","17":"\/documentation\/Bitcoin\/Running#Alice","3":"\/documentation\/Bitcoin\/GettingStarted#Import-the-framework","7":"\/tutorials"},"pathHierarchy":{"tutorialOverviewContainer":7,"tutorialContainer":18,"articlesContainer":11,"nodes":[{"name":"Add-the-package"},{"name":"Mac"},{"children":[{"kind":"anchor","nodeID":19},{"kind":"anchor","nodeID":8},{"nodeID":10,"kind":"anchor"},{"nodeID":17,"kind":"anchor"},{"kind":"anchor","nodeID":20},{"kind":"anchor","nodeID":15},{"nodeID":22,"kind":"anchor"},{"nodeID":5,"kind":"anchor"},{"kind":"anchor","nodeID":23},{"nodeID":21,"kind":"anchor"}],"name":"Running"},{"name":"Import-the-framework"},{"name":"GettingStarted","children":[{"kind":"anchor","nodeID":0},{"nodeID":3,"kind":"anchor"},{"kind":"anchor","nodeID":12},{"kind":"anchor","nodeID":6}]},{"name":"Build-executable-docker-images"},{"name":"Preparation"},{"name":"tutorials"},{"name":"Setup"},{"name":"Overview"},{"name":"Carol-Bitcoin-Core"},{"children":[{"nodeID":16,"kind":"article"},{"kind":"article","nodeID":4},{"nodeID":14,"kind":"anchor"},{"nodeID":2,"kind":"article"},{"kind":"anchor","nodeID":9}],"symbolID":{"precise":"Bitcoin","interfaceLanguage":"swift"},"name":"Bitcoin"},{"name":"Mine-a-transaction"},{"name":"Docker-instructions"},{"name":"Essentials"},{"name":"Run-using-the-swift-command"},{"children":[{"nodeID":25,"kind":"anchor"},{"kind":"anchor","nodeID":24},{"kind":"anchor","nodeID":13},{"kind":"anchor","nodeID":1}],"name":"Building"},{"name":"Alice"},{"name":"Bitcoin"},{"name":"Run-with-docker"},{"name":"Bob"},{"name":"Simulate-a-muilt-node-network"},{"name":"Build-and-run-executables-directly"},{"name":"Interactive-container"},{"name":"Linux"},{"name":"Executable-image"}],"modules":[11]}}