[{"path":"\/documentation\/bitcoin\/gettingstarted","title":"Getting Started","kind":"org.swift.docc.kind.article","abstract":[{"type":"text","text":"To start using Swift Bitcoin just add it as a dependency to your package manifest."}],"referenceURL":"doc:\/\/Bitcoin\/documentation\/Bitcoin\/GettingStarted","availableLanguages":["swift"],"language":"swift"},{"abstract":[{"type":"text","text":"Pure-Swift Bitcoin client implementation with full node capabilities."}],"title":"Swift Bitcoin","language":"swift","usr":"Bitcoin","kind":"org.swift.docc.kind.module","referenceURL":"doc:\/\/Bitcoin\/documentation\/Bitcoin","path":"\/documentation\/bitcoin","availableLanguages":["swift"]}]